{"address":"Липецкая область, г.Липецк, ул. Валентины Терешковой, д.13, корп.В","apartmentsCount":"225","building":{"monthDelay":"21.26","nallsquare":"19038","postponeM2":"10380.0","postponePercent":"54.52"},"courseOfConstruction":{"build":{"allApartments":"211","gk":"2","pt":"0"},"finish":{"allApartments":"14","gk":"2","pt":"0"},"stageApartmentCount":"225","stop":{"allApartments":"0","gk":"0","pt":"0"}},"developers_count":"3","endToInvestors":"false","ratingErz":["3.00","3.00"],"full_name":"СУ-11 Липецкстрой","gk_count":"2","htmlPage":{"description":"СУ-11 Липецкстрой - цены на квартиры в новостройках, описание компании, контакты.","index":"index_follow","title":"СУ-11 Липецкстрой - информация о бренде, новостройки на карте, рейтинг - ЕРЗ.","url":"su-11-lipeckstroj-3237646001"},"id":"3237646001","input2016":{"monthDelay":"2.3","nallsquare":"20857","postponeM2":"4005.0","postponePercent":"19.2"},"input2017":{"monthDelay":"0.0","nallsquare":"17489","postponeM2":"0.0","postponePercent":"0.0"},"input2018":{"monthDelay":"1.45","nallsquare":"16052","postponeM2":"8035.0","postponePercent":"50.06"},"isHiddenConsumer":"0","logotype":"erz-rest/api/v1/document?id=3237651001&type=LOGO&nocache=1562425722384","management":{"management":{"surname":"Григорьев","name":"Виктор","secondname":"Александрович","position":"генеральный директор"}},"maxDedit":"2019-04-18","mentioning":{"mentioning":[{"title":"Липецкий долгострой будут завершать местные строители","annotation":"Как сообщает пресс-служба регионального Арбитражного суда, заявление ООО СУ-11 «Липецкстрой-Л» о намерении стать приобретателем долгостроя в Липецке удовлетворено. Ситуация касается жилого дома на Агрономической, 4 и земельного участка. Так компания исполнит обязательства застройщика ООО «Риэлторский центр «Строй-Град» перед дольщиками.","rating":"положительная","source":"Информационно-справочный портал Gorod48.ru","date":"13 июля 2018","vlink":"https://gorod48.ru/news/1052276/"},{"title":"«Мы эти обещания слышим уже давно! Достройте нам наши дома!»","annotation":"На встрече главы Липецка с обманутыми дольщиками эмоции перехлестывали через край.По домам обанкротившегося «Строй-Града» перед дольщиками выступил представитель тамбовской формы «Сталь-М», который пообещал сдать к 1 мая объект на углу улиц Фрунзе-Неделина. А Александр Пушилин сообщил, что дом на улице Агрономической достроит СУ-11. Работы на нем начнутся в конце февраля.","rating":"положительная","source":"Информационно-справочный портал Gorod48.ru","date":"08 февраля 2018","vlink":"https://gorod48.ru/news/625805/"}]},"name":"СУ-11 Липецкстрой","newsCount":"0","ntype":"0","pt_count":"0","rating_rask":"В2","regionsDate":"01.07.2019","regions_count":"1","salesDepartmentPhone":"(4742) 357305, (4742) 357310","salesRegion":{"salesRegion":{"apartmentsCount":"225","averagePrice":"43169","gkCount":"4","isHiddenConsumer":"0","ptCount":"0","regionKey":"143368001","regionName":"Липецкая область"}},"salesRegionCount":"1","site":"su11.ru/","place":"1170","urlId":"su-11-lipeckstroj-3237646001","viewCount":"416","volume_of_building":"19038","year_of_foundation":"1967"}