[
  {
    "apartmentsCountAll": 115,
    "apartmentsCountSales": 68,
    "buildingVolume": "174363",
    "coefficientRating": "100",
    "complexesCountAll": 10,
    "complexesCountSales": 1,
    "filteredApartmentsCount": 68,
    "filteredComplexCount": 1,
    "filteredGkCount": 0,
    "filteredOrgCount": 1,
    "filteredPtCount": 0,
    "foundationYear": "1975",
    "gkCountSales": 1,
    "id": "2968328001",
    "maxApartmentCostM2": "46500",
    "maxCostMillion": "4.31",
    "minApartmentCostM2": "42500",
    "minCostMillion": "1.6",
    "name": "СК ВГС",
    "orgCountAll": 5,
    "orgCountSales": 1,
    "ptCountSales": 0,
    "rating": "5",
    "region": "Вологодская область",
    "regionKey": "142254001",
    "regionPlace": "1",
    "rfPlace": "129",
    "shareRegionPercent": "14.86",
    "urlId": "stroitelnaja-kompanija-vologdagrazhdanstroj-2968328001"
  },
  {
    "apartmentsCountAll": 301,
    "apartmentsCountSales": 292,
    "buildingVolume": "118771",
    "coefficientRating": "68.12",
    "complexesCountAll": 9,
    "complexesCountSales": 4,
    "filteredApartmentsCount": 292,
    "filteredComplexCount": 4,
    "filteredGkCount": 0,
    "filteredOrgCount": 1,
    "filteredPtCount": 0,
    "foundationYear": "2003",
    "gkCountSales": 4,
    "id": "5874016001",
    "maxApartmentCostM2": "42746",
    "maxCostMillion": "2.61",
    "minApartmentCostM2": "21013",
    "minCostMillion": "0.73",
    "name": "ЖилСтройИндустрия",
    "orgCountAll": 1,
    "orgCountSales": 1,
    "ptCountSales": 0,
    "rating": "1",
    "region": "Вологодская область",
    "regionKey": "142254001",
    "regionPlace": "2",
    "rfPlace": "219",
    "shareRegionPercent": "10.12",
    "urlId": "zhilishhno-stroitelnaja-industrija-5874016001"
  },
  {
    "apartmentsCountAll": 29,
    "apartmentsCountSales": 24,
    "buildingVolume": "92847",
    "coefficientRating": "53.25",
    "complexesCountAll": 8,
    "complexesCountSales": 2,
    "filteredApartmentsCount": 24,
    "filteredComplexCount": 2,
    "filteredGkCount": 0,
    "filteredOrgCount": 2,
    "filteredPtCount": 0,
    "foundationYear": "1964",
    "gkCountSales": 2,
    "id": "5343984001",
    "maxApartmentCostM2": "43252",
    "maxCostMillion": "2.59",
    "minApartmentCostM2": "35000",
    "minCostMillion": "1.13",
    "name": "Горстройзаказчик",
    "orgCountAll": 3,
    "orgCountSales": 2,
    "ptCountSales": 0,
    "rating": "0.5",
    "region": "Вологодская область",
    "regionKey": "142254001",
    "regionPlace": "3",
    "rfPlace": "288",
    "shareRegionPercent": "7.91",
    "urlId": "gorstrojzakazchik-5343984001"
  },
  {
    "apartmentsCountAll": 121,
    "apartmentsCountSales": 53,
    "buildingVolume": "90588",
    "coefficientRating": "51.95",
    "complexesCountAll": 7,
    "complexesCountSales": 3,
    "filteredApartmentsCount": 53,
    "filteredComplexCount": 3,
    "filteredGkCount": 0,
    "filteredOrgCount": 1,
    "filteredPtCount": 0,
    "foundationYear": "2011",
    "gkCountSales": 3,
    "id": "5889139001",
    "maxApartmentCostM2": "47250",
    "maxCostMillion": "3.07",
    "minApartmentCostM2": "36551",
    "minCostMillion": "1.19",
    "name": "Жилстройзаказчик",
    "orgCountAll": 1,
    "orgCountSales": 1,
    "ptCountSales": 0,
    "rating": "5",
    "region": "Вологодская область",
    "regionKey": "142254001",
    "regionPlace": "4",
    "rfPlace": "300",
    "shareRegionPercent": "7.72",
    "urlId": "zhilstrojzakazchik-5889139001"
  },
  {
    "apartmentsCountAll": 433,
    "apartmentsCountSales": 102,
    "buildingVolume": "85651",
    "coefficientRating": "49.12",
    "complexesCountAll": 6,
    "complexesCountSales": 3,
    "filteredApartmentsCount": 102,
    "filteredComplexCount": 3,
    "filteredGkCount": 0,
    "filteredOrgCount": 1,
    "filteredPtCount": 0,
    "foundationYear": "2006",
    "gkCountSales": 3,
    "id": "5830520001",
    "maxApartmentCostM2": "48076",
    "maxCostMillion": "3.91",
    "minApartmentCostM2": "39030",
    "minCostMillion": "1.39",
    "name": "ВСЗ",
    "orgCountAll": 1,
    "orgCountSales": 1,
    "ptCountSales": 0,
    "rating": "5",
    "region": "Вологодская область",
    "regionKey": "142254001",
    "regionPlace": "5",
    "rfPlace": "314",
    "shareRegionPercent": "7.3",
    "urlId": "vologdastrojzakazchik-5830520001"
  },
  {
    "apartmentsCountAll": 1,
    "apartmentsCountSales": 1,
    "buildingVolume": "75568",
    "coefficientRating": "43.34",
    "complexesCountAll": 1,
    "complexesCountSales": 1,
    "filteredApartmentsCount": 1,
    "filteredComplexCount": 1,
    "filteredGkCount": 0,
    "filteredOrgCount": 1,
    "filteredPtCount": 0,
    "foundationYear": "2017",
    "gkCountSales": 1,
    "id": "9433440001",
    "maxApartmentCostM2": "37093",
    "maxCostMillion": "1.48",
    "minApartmentCostM2": "37093",
    "minCostMillion": "1.48",
    "name": "ТК Групп",
    "orgCountAll": 1,
    "orgCountSales": 1,
    "ptCountSales": 0,
    "region": "Вологодская область",
    "regionKey": "142254001",
    "regionPlace": "6",
    "rfPlace": "361",
    "shareRegionPercent": "6.44",
    "urlId": "tk-grupp-9433440001"
  },
  {
    "apartmentsCountAll": 170,
    "apartmentsCountSales": 55,
    "buildingVolume": "75087",
    "coefficientRating": "43.06",
    "complexesCountAll": 1,
    "complexesCountSales": 1,
    "filteredApartmentsCount": 55,
    "filteredComplexCount": 1,
    "filteredGkCount": 0,
    "filteredOrgCount": 1,
    "filteredPtCount": 0,
    "foundationYear": "2009",
    "gkCountSales": 1,
    "id": "7910476001",
    "maxApartmentCostM2": "36750",
    "maxCostMillion": "1.96",
    "minApartmentCostM2": "35000",
    "minCostMillion": "1.23",
    "name": "Южный",
    "orgCountAll": 1,
    "orgCountSales": 1,
    "ptCountSales": 0,
    "region": "Вологодская область",
    "regionKey": "142254001",
    "regionPlace": "7",
    "rfPlace": "367",
    "shareRegionPercent": "6.4",
    "urlId": "-juzhnyj-7910476001"
  },
  {
    "apartmentsCountAll": 1074,
    "apartmentsCountSales": 212,
    "buildingVolume": "42563",
    "coefficientRating": "24.41",
    "complexesCountAll": 6,
    "complexesCountSales": 5,
    "filteredApartmentsCount": 212,
    "filteredComplexCount": 5,
    "filteredGkCount": 0,
    "filteredOrgCount": 1,
    "filteredPtCount": 0,
    "foundationYear": "1989",
    "gkCountSales": 5,
    "id": "5823519001",
    "maxApartmentCostM2": "45837",
    "maxCostMillion": "5.17",
    "minApartmentCostM2": "37136",
    "minCostMillion": "1.14",
    "name": "СК Железобетон-12",
    "orgCountAll": 1,
    "orgCountSales": 1,
    "ptCountSales": 0,
    "rating": "4.5",
    "region": "Вологодская область",
    "regionKey": "142254001",
    "regionPlace": "8",
    "rfPlace": "631",
    "shareRegionPercent": "3.63",
    "urlId": "stroitelnaja-kompanija-zhelezobeton-12-5823519001"
  },
  {
    "apartmentsCountAll": 17,
    "apartmentsCountSales": 17,
    "buildingVolume": "32870",
    "coefficientRating": "18.85",
    "complexesCountAll": 2,
    "complexesCountSales": 1,
    "filteredApartmentsCount": 17,
    "filteredComplexCount": 1,
    "filteredGkCount": 0,
    "filteredOrgCount": 1,
    "filteredPtCount": 0,
    "foundationYear": "2013",
    "gkCountSales": 1,
    "id": "9845052001",
    "maxApartmentCostM2": "48015",
    "maxCostMillion": "3.86",
    "minApartmentCostM2": "45002",
    "minCostMillion": "1.31",
    "name": "Инвестцентр",
    "orgCountAll": 1,
    "orgCountSales": 1,
    "ptCountSales": 0,
    "region": "Вологодская область",
    "regionKey": "142254001",
    "regionPlace": "9",
    "rfPlace": "782",
    "shareRegionPercent": "2.8",
    "urlId": "-investcentr-9845052001"
  },
  {
    "apartmentsCountAll": 388,
    "apartmentsCountSales": 159,
    "buildingVolume": "29587",
    "coefficientRating": "16.97",
    "complexesCountAll": 8,
    "complexesCountSales": 4,
    "filteredApartmentsCount": 159,
    "filteredComplexCount": 4,
    "filteredGkCount": 0,
    "filteredOrgCount": 2,
    "filteredPtCount": 0,
    "foundationYear": "1990",
    "gkCountSales": 4,
    "id": "5904480001",
    "maxApartmentCostM2": "49966",
    "maxCostMillion": "4.43",
    "minApartmentCostM2": "37616",
    "minCostMillion": "1.39",
    "name": "Реал-СВ",
    "orgCountAll": 2,
    "orgCountSales": 2,
    "ptCountSales": 0,
    "rating": "0",
    "region": "Вологодская область",
    "regionKey": "142254001",
    "regionPlace": "10",
    "rfPlace": "838",
    "shareRegionPercent": "2.52",
    "urlId": "real-sv-5904480001"
  },
  {
    "apartmentsCountAll": 212,
    "apartmentsCountSales": 212,
    "buildingVolume": "27162",
    "coefficientRating": "15.58",
    "complexesCountAll": 5,
    "complexesCountSales": 2,
    "filteredApartmentsCount": 212,
    "filteredComplexCount": 2,
    "filteredGkCount": 0,
    "filteredOrgCount": 1,
    "filteredPtCount": 0,
    "foundationYear": "2002",
    "gkCountSales": 2,
    "id": "5830865001",
    "maxApartmentCostM2": "51000",
    "maxCostMillion": "5.46",
    "minApartmentCostM2": "38500",
    "minCostMillion": "1.41",
    "name": "Вологдаагрострой",
    "orgCountAll": 1,
    "orgCountSales": 1,
    "ptCountSales": 0,
    "rating": "5",
    "region": "Вологодская область",
    "regionKey": "142254001",
    "regionPlace": "11",
    "rfPlace": "892",
    "shareRegionPercent": "2.31",
    "urlId": "vologdaagrostroj-5830865001"
  },
  {
    "apartmentsCountAll": 5,
    "apartmentsCountSales": 4,
    "buildingVolume": "25618",
    "coefficientRating": "14.69",
    "complexesCountAll": 3,
    "complexesCountSales": 1,
    "filteredApartmentsCount": 4,
    "filteredComplexCount": 1,
    "filteredGkCount": 0,
    "filteredOrgCount": 1,
    "filteredPtCount": 0,
    "foundationYear": "2002",
    "gkCountSales": 1,
    "id": "5905973001",
    "maxApartmentCostM2": "38647",
    "maxCostMillion": "2.12",
    "minApartmentCostM2": "36508",
    "minCostMillion": "0.96",
    "name": "Компания МК-Строй",
    "orgCountAll": 1,
    "orgCountSales": 1,
    "ptCountSales": 0,
    "region": "Вологодская область",
    "regionKey": "142254001",
    "regionPlace": "12",
    "rfPlace": "931",
    "shareRegionPercent": "2.18",
    "urlId": "kompanija-mk-stroj-5905973001"
  },
  {
    "apartmentsCountAll": 12,
    "apartmentsCountSales": 7,
    "buildingVolume": "23506",
    "coefficientRating": "13.48",
    "complexesCountAll": 2,
    "complexesCountSales": 2,
    "filteredApartmentsCount": 7,
    "filteredComplexCount": 2,
    "filteredGkCount": 0,
    "filteredOrgCount": 1,
    "filteredPtCount": 0,
    "foundationYear": "2011",
    "gkCountSales": 2,
    "id": "5866912001",
    "maxApartmentCostM2": "48479",
    "maxCostMillion": "2.55",
    "minApartmentCostM2": "40979",
    "minCostMillion": "1.34",
    "name": "Арсенал",
    "orgCountAll": 1,
    "orgCountSales": 1,
    "ptCountSales": 0,
    "rating": "0.5",
    "region": "Вологодская область",
    "regionKey": "142254001",
    "regionPlace": "14",
    "rfPlace": "989",
    "shareRegionPercent": "2",
    "urlId": "arsenal-5866912001"
  },
  {
    "apartmentsCountAll": 60,
    "apartmentsCountSales": 35,
    "buildingVolume": "19222",
    "coefficientRating": "11.02",
    "complexesCountAll": 2,
    "complexesCountSales": 2,
    "filteredApartmentsCount": 35,
    "filteredComplexCount": 2,
    "filteredGkCount": 0,
    "filteredOrgCount": 2,
    "filteredPtCount": 0,
    "foundationYear": "2008",
    "gkCountSales": 2,
    "id": "5752104001",
    "maxApartmentCostM2": "53980",
    "maxCostMillion": "4.42",
    "minApartmentCostM2": "39900",
    "minCostMillion": "1.07",
    "name": "СМХ",
    "orgCountAll": 2,
    "orgCountSales": 2,
    "ptCountSales": 0,
    "rating": "0.5",
    "region": "Вологодская область",
    "regionKey": "142254001",
    "regionPlace": "15",
    "rfPlace": "1162",
    "shareRegionPercent": "1.67",
    "urlId": "strojmonolit-kholding-5752104001"
  },
  {
    "apartmentsCountAll": 3,
    "apartmentsCountSales": 3,
    "buildingVolume": "15135",
    "coefficientRating": "8.68",
    "complexesCountAll": 3,
    "complexesCountSales": 2,
    "filteredApartmentsCount": 3,
    "filteredComplexCount": 2,
    "filteredGkCount": 0,
    "filteredOrgCount": 1,
    "filteredPtCount": 0,
    "foundationYear": "2007",
    "gkCountSales": 2,
    "id": "4138505001",
    "maxApartmentCostM2": "47077",
    "maxCostMillion": "3.06",
    "minApartmentCostM2": "39492",
    "minCostMillion": "1.09",
    "name": "СК Нова",
    "orgCountAll": 2,
    "orgCountSales": 1,
    "ptCountSales": 0,
    "rating": "3.5",
    "region": "Вологодская область",
    "regionKey": "142254001",
    "regionPlace": "16",
    "rfPlace": "1380",
    "shareRegionPercent": "1.29",
    "urlId": "stroitelnaja-kompanija-nova-4138505001"
  },
  {
    "apartmentsCountAll": 275,
    "apartmentsCountSales": 177,
    "buildingVolume": "10824",
    "coefficientRating": "6.21",
    "complexesCountAll": 2,
    "complexesCountSales": 2,
    "filteredApartmentsCount": 177,
    "filteredComplexCount": 2,
    "filteredGkCount": 0,
    "filteredOrgCount": 1,
    "filteredPtCount": 0,
    "gkCountSales": 2,
    "id": "6262812001",
    "maxApartmentCostM2": "56100",
    "maxCostMillion": "6.75",
    "minApartmentCostM2": "39500",
    "minCostMillion": "0.87",
    "name": "АГ ЭСТЕЙТ",
    "orgCountAll": 1,
    "orgCountSales": 1,
    "ptCountSales": 0,
    "region": "Вологодская область",
    "regionKey": "142254001",
    "regionPlace": "17",
    "rfPlace": "1720",
    "shareRegionPercent": "0.92",
    "urlId": "ag-estejt-6262812001"
  },
  {
    "apartmentsCountAll": 2,
    "apartmentsCountSales": 2,
    "buildingVolume": "10046",
    "coefficientRating": "5.76",
    "complexesCountAll": 1,
    "complexesCountSales": 1,
    "filteredApartmentsCount": 2,
    "filteredComplexCount": 1,
    "filteredGkCount": 0,
    "filteredOrgCount": 1,
    "filteredPtCount": 0,
    "foundationYear": "2017",
    "gkCountSales": 1,
    "id": "9721265001",
    "maxApartmentCostM2": "40500",
    "maxCostMillion": "1.62",
    "minApartmentCostM2": "40500",
    "minCostMillion": "1.5",
    "name": "ИнвестСтрой",
    "orgCountAll": 1,
    "orgCountSales": 1,
    "ptCountSales": 0,
    "rating": "0.5",
    "region": "Вологодская область",
    "regionKey": "142254001",
    "regionPlace": "18",
    "rfPlace": "1791",
    "shareRegionPercent": "0.86",
    "urlId": "-investstroj-9721265001"
  },
  {
    "apartmentsCountAll": 1,
    "apartmentsCountSales": 1,
    "buildingVolume": "9794",
    "coefficientRating": "5.62",
    "complexesCountAll": 5,
    "complexesCountSales": 1,
    "filteredApartmentsCount": 1,
    "filteredComplexCount": 1,
    "filteredGkCount": 0,
    "filteredOrgCount": 1,
    "filteredPtCount": 0,
    "foundationYear": "2006",
    "gkCountSales": 1,
    "id": "5895698001",
    "maxApartmentCostM2": "47000",
    "maxCostMillion": "2.53",
    "minApartmentCostM2": "47000",
    "minCostMillion": "2.53",
    "name": "Компания Инвестстройзаказчик",
    "orgCountAll": 1,
    "orgCountSales": 1,
    "ptCountSales": 0,
    "rating": "5",
    "region": "Вологодская область",
    "regionKey": "142254001",
    "regionPlace": "21",
    "rfPlace": "1826",
    "shareRegionPercent": "0.83",
    "urlId": "kompanija-investstrojzakazchik-5895698001"
  },
  {
    "apartmentsCountAll": 81,
    "apartmentsCountSales": 72,
    "buildingVolume": "9641",
    "coefficientRating": "5.53",
    "complexesCountAll": 2,
    "complexesCountSales": 1,
    "filteredApartmentsCount": 72,
    "filteredComplexCount": 1,
    "filteredGkCount": 0,
    "filteredOrgCount": 1,
    "filteredPtCount": 0,
    "foundationYear": "2002",
    "gkCountSales": 1,
    "id": "5886866001",
    "maxApartmentCostM2": "44000",
    "maxCostMillion": "4.02",
    "minApartmentCostM2": "41000",
    "minCostMillion": "1.7",
    "name": "Феникс",
    "orgCountAll": 1,
    "orgCountSales": 1,
    "ptCountSales": 0,
    "rating": "5",
    "region": "Вологодская область",
    "regionKey": "142254001",
    "regionPlace": "22",
    "rfPlace": "1848",
    "shareRegionPercent": "0.82",
    "urlId": "feniks-5886866001"
  },
  {
    "apartmentsCountAll": 2,
    "apartmentsCountSales": 2,
    "buildingVolume": "8753",
    "coefficientRating": "5.02",
    "complexesCountAll": 2,
    "complexesCountSales": 1,
    "filteredApartmentsCount": 2,
    "filteredComplexCount": 1,
    "filteredGkCount": 0,
    "filteredOrgCount": 1,
    "filteredPtCount": 0,
    "gkCountSales": 1,
    "id": "6271539001",
    "maxApartmentCostM2": "46250",
    "maxCostMillion": "1.85",
    "minApartmentCostM2": "44433",
    "minCostMillion": "1.7",
    "name": "СК Стройснаб",
    "orgCountAll": 1,
    "orgCountSales": 1,
    "ptCountSales": 0,
    "region": "Вологодская область",
    "regionKey": "142254001",
    "regionPlace": "23",
    "rfPlace": "1927",
    "shareRegionPercent": "0.76",
    "urlId": "stroitelnaja-kompanija-strojsnab-6271539001"
  },
  {
    "apartmentsCountAll": 147,
    "apartmentsCountSales": 110,
    "buildingVolume": "8360",
    "coefficientRating": "4.79",
    "complexesCountAll": 1,
    "complexesCountSales": 1,
    "filteredApartmentsCount": 110,
    "filteredComplexCount": 1,
    "filteredGkCount": 0,
    "filteredOrgCount": 1,
    "filteredPtCount": 0,
    "foundationYear": "2015",
    "gkCountSales": 1,
    "id": "6022707001",
    "maxApartmentCostM2": "44625",
    "maxCostMillion": "2.82",
    "minApartmentCostM2": "39900",
    "minCostMillion": "1.08",
    "name": "Соло-Строй",
    "orgCountAll": 1,
    "orgCountSales": 1,
    "ptCountSales": 0,
    "region": "Вологодская область",
    "regionKey": "142254001",
    "regionPlace": "24",
    "rfPlace": "1975",
    "shareRegionPercent": "0.73",
    "urlId": "solo-stroj-6022707001"
  },
  {
    "apartmentsCountAll": 1,
    "apartmentsCountSales": 1,
    "buildingVolume": "8310",
    "coefficientRating": "4.77",
    "complexesCountAll": 3,
    "complexesCountSales": 1,
    "filteredApartmentsCount": 1,
    "filteredComplexCount": 1,
    "filteredGkCount": 0,
    "filteredOrgCount": 1,
    "filteredPtCount": 0,
    "foundationYear": "2002",
    "gkCountSales": 1,
    "id": "6015947001",
    "maxApartmentCostM2": "44849",
    "maxCostMillion": "1.75",
    "minApartmentCostM2": "44849",
    "minCostMillion": "1.75",
    "name": "СИЦ",
    "orgCountAll": 1,
    "orgCountSales": 1,
    "ptCountSales": 0,
    "rating": "2.5",
    "region": "Вологодская область",
    "regionKey": "142254001",
    "regionPlace": "25",
    "rfPlace": "1996",
    "shareRegionPercent": "0.71",
    "urlId": "stroitelnyj-investicionnyj-centr-6015947001"
  },
  {
    "apartmentsCountAll": 5,
    "apartmentsCountSales": 2,
    "buildingVolume": "8241",
    "coefficientRating": "4.73",
    "complexesCountAll": 1,
    "complexesCountSales": 1,
    "filteredApartmentsCount": 2,
    "filteredComplexCount": 1,
    "filteredGkCount": 0,
    "filteredOrgCount": 1,
    "filteredPtCount": 0,
    "foundationYear": "2016",
    "gkCountSales": 1,
    "id": "10060517001",
    "maxApartmentCostM2": "52000",
    "maxCostMillion": "2.03",
    "minApartmentCostM2": "50000",
    "minCostMillion": "1.75",
    "name": "СК Ренессанс",
    "orgCountAll": 1,
    "orgCountSales": 1,
    "ptCountSales": 0,
    "region": "Вологодская область",
    "regionKey": "142254001",
    "regionPlace": "26",
    "rfPlace": "1991",
    "shareRegionPercent": "0.72",
    "urlId": "-stroitelnaja-kompanija-renessans-10060517001"
  },
  {
    "apartmentsCountAll": 6,
    "apartmentsCountSales": 6,
    "buildingVolume": "8032",
    "coefficientRating": "4.61",
    "complexesCountAll": 1,
    "complexesCountSales": 1,
    "filteredApartmentsCount": 6,
    "filteredComplexCount": 1,
    "filteredGkCount": 0,
    "filteredOrgCount": 1,
    "filteredPtCount": 0,
    "foundationYear": "2015",
    "gkCountSales": 1,
    "id": "9966236001",
    "maxApartmentCostM2": "45327",
    "maxCostMillion": "3.67",
    "minApartmentCostM2": "42187",
    "minCostMillion": "1.14",
    "name": "СпецРегионСтрой",
    "orgCountAll": 1,
    "orgCountSales": 1,
    "ptCountSales": 0,
    "region": "Вологодская область",
    "regionKey": "142254001",
    "regionPlace": "27",
    "rfPlace": "2016",
    "shareRegionPercent": "0.7",
    "urlId": "-specregionstroj-9966236001"
  },
  {
    "apartmentsCountAll": 3,
    "apartmentsCountSales": 3,
    "buildingVolume": "7920",
    "coefficientRating": "4.54",
    "complexesCountAll": 1,
    "complexesCountSales": 1,
    "filteredApartmentsCount": 3,
    "filteredComplexCount": 1,
    "filteredGkCount": 0,
    "filteredOrgCount": 1,
    "filteredPtCount": 0,
    "foundationYear": "2012",
    "gkCountSales": 1,
    "id": "6147365001",
    "maxApartmentCostM2": "47500",
    "maxCostMillion": "3.22",
    "minApartmentCostM2": "46500",
    "minCostMillion": "2.22",
    "name": "СИК Монолит-Строй",
    "orgCountAll": 1,
    "orgCountSales": 1,
    "ptCountSales": 0,
    "region": "Вологодская область",
    "regionKey": "142254001",
    "regionPlace": "28",
    "rfPlace": "2046",
    "shareRegionPercent": "0.67",
    "urlId": "stroitelnaja-investicionnaja-kompanija-monolit-stroj-6147365001"
  },
  {
    "apartmentsCountAll": 9,
    "apartmentsCountSales": 9,
    "buildingVolume": "5258",
    "coefficientRating": "3.02",
    "complexesCountAll": 2,
    "complexesCountSales": 1,
    "filteredApartmentsCount": 9,
    "filteredComplexCount": 1,
    "filteredGkCount": 0,
    "filteredOrgCount": 2,
    "filteredPtCount": 0,
    "foundationYear": "2011",
    "gkCountSales": 1,
    "id": "6020070001",
    "maxApartmentCostM2": "44688",
    "maxCostMillion": "2.19",
    "minApartmentCostM2": "42621",
    "minCostMillion": "1.43",
    "name": "ВЖС",
    "orgCountAll": 2,
    "orgCountSales": 2,
    "ptCountSales": 0,
    "rating": "3.5",
    "region": "Вологодская область",
    "regionKey": "142254001",
    "regionPlace": "32",
    "rfPlace": "2454",
    "shareRegionPercent": "0.46",
    "urlId": "vologdazhilstroj-6020070001"
  },
  {
    "apartmentsCountAll": 6,
    "apartmentsCountSales": 6,
    "buildingVolume": "5163",
    "coefficientRating": "2.96",
    "complexesCountAll": 1,
    "complexesCountSales": 1,
    "filteredApartmentsCount": 6,
    "filteredComplexCount": 1,
    "filteredGkCount": 0,
    "filteredOrgCount": 1,
    "filteredPtCount": 0,
    "foundationYear": "2013",
    "gkCountSales": 1,
    "id": "5904387001",
    "maxApartmentCostM2": "41825",
    "maxCostMillion": "1.99",
    "minApartmentCostM2": "38110",
    "minCostMillion": "1.25",
    "name": "КапиталЖилСтрой",
    "orgCountAll": 1,
    "orgCountSales": 1,
    "ptCountSales": 0,
    "rating": "4.5",
    "region": "Вологодская область",
    "regionKey": "142254001",
    "regionPlace": "34",
    "rfPlace": "2469",
    "shareRegionPercent": "0.45",
    "urlId": "kapitalzhilstroj-5904387001"
  },
  {
    "apartmentsCountAll": 2,
    "apartmentsCountSales": 2,
    "buildingVolume": "4996",
    "coefficientRating": "2.87",
    "complexesCountAll": 2,
    "complexesCountSales": 1,
    "filteredApartmentsCount": 2,
    "filteredComplexCount": 1,
    "filteredGkCount": 0,
    "filteredOrgCount": 1,
    "filteredPtCount": 0,
    "foundationYear": "2010",
    "gkCountSales": 1,
    "id": "6052878001",
    "maxApartmentCostM2": "45000",
    "maxCostMillion": "1.95",
    "minApartmentCostM2": "45000",
    "minCostMillion": "1.49",
    "name": "АЛЬТЕНЗА",
    "orgCountAll": 1,
    "orgCountSales": 1,
    "ptCountSales": 0,
    "region": "Вологодская область",
    "regionKey": "142254001",
    "regionPlace": "35",
    "rfPlace": "2500",
    "shareRegionPercent": "0.43",
    "urlId": "altenza-6052878001"
  },
  {
    "apartmentsCountAll": 2,
    "apartmentsCountSales": 2,
    "buildingVolume": "4883",
    "coefficientRating": "2.8",
    "complexesCountAll": 3,
    "complexesCountSales": 1,
    "filteredApartmentsCount": 2,
    "filteredComplexCount": 1,
    "filteredGkCount": 0,
    "filteredOrgCount": 1,
    "filteredPtCount": 0,
    "gkCountSales": 1,
    "id": "6064156001",
    "maxApartmentCostM2": "53001",
    "maxCostMillion": "3.42",
    "minApartmentCostM2": "52074",
    "minCostMillion": "2.03",
    "name": "ГК РСЗ",
    "orgCountAll": 1,
    "orgCountSales": 1,
    "ptCountSales": 0,
    "region": "Вологодская область",
    "regionKey": "142254001",
    "regionPlace": "36",
    "rfPlace": "2526",
    "shareRegionPercent": "0.42",
    "urlId": "gruppa-kompanij-remstrojzakazchik-6064156001"
  },
  {
    "apartmentsCountAll": 11,
    "apartmentsCountSales": 8,
    "buildingVolume": "4807",
    "coefficientRating": "2.76",
    "complexesCountAll": 9,
    "complexesCountSales": 3,
    "filteredApartmentsCount": 8,
    "filteredComplexCount": 3,
    "filteredGkCount": 0,
    "filteredOrgCount": 1,
    "filteredPtCount": 0,
    "gkCountSales": 3,
    "id": "4139991001",
    "maxApartmentCostM2": "60409",
    "maxCostMillion": "6.5",
    "minApartmentCostM2": "33012",
    "minCostMillion": "2.0",
    "name": "СТРОИМ 35",
    "orgCountAll": 2,
    "orgCountSales": 1,
    "ptCountSales": 0,
    "region": "Вологодская область",
    "regionKey": "142254001",
    "regionPlace": "37",
    "rfPlace": "2537",
    "shareRegionPercent": "0.41",
    "urlId": "stroim-35-4139991001"
  },
  {
    "apartmentsCountAll": 9,
    "apartmentsCountSales": 2,
    "buildingVolume": "4528",
    "coefficientRating": "2.6",
    "complexesCountAll": 1,
    "complexesCountSales": 1,
    "filteredApartmentsCount": 2,
    "filteredComplexCount": 1,
    "filteredGkCount": 0,
    "filteredOrgCount": 1,
    "filteredPtCount": 0,
    "foundationYear": "2004",
    "gkCountSales": 1,
    "id": "5486924001",
    "maxApartmentCostM2": "43012",
    "maxCostMillion": "1.98",
    "minApartmentCostM2": "43000",
    "minCostMillion": "1.78",
    "name": "ДомСтрой",
    "orgCountAll": 1,
    "orgCountSales": 1,
    "ptCountSales": 0,
    "region": "Вологодская область",
    "regionKey": "142254001",
    "regionPlace": "38",
    "rfPlace": "2583",
    "shareRegionPercent": "0.39",
    "urlId": "domstroj-5486924001"
  },
  {
    "apartmentsCountAll": 38,
    "apartmentsCountSales": 24,
    "buildingVolume": "4509",
    "coefficientRating": "2.59",
    "complexesCountAll": 2,
    "complexesCountSales": 1,
    "filteredApartmentsCount": 24,
    "filteredComplexCount": 1,
    "filteredGkCount": 0,
    "filteredOrgCount": 1,
    "filteredPtCount": 0,
    "foundationYear": "2016",
    "gkCountSales": 1,
    "id": "7911493001",
    "maxApartmentCostM2": "46170",
    "maxCostMillion": "4.3",
    "minApartmentCostM2": "41737",
    "minCostMillion": "1.75",
    "name": "Новостройки",
    "orgCountAll": 2,
    "orgCountSales": 1,
    "ptCountSales": 0,
    "region": "Вологодская область",
    "regionKey": "142254001",
    "regionPlace": "39",
    "rfPlace": "2585",
    "shareRegionPercent": "0.38",
    "urlId": "-novostrojki-7911493001"
  },
  {
    "apartmentsCountAll": 2,
    "apartmentsCountSales": 2,
    "buildingVolume": "4350",
    "coefficientRating": "2.49",
    "complexesCountAll": 1,
    "complexesCountSales": 1,
    "filteredApartmentsCount": 2,
    "filteredComplexCount": 1,
    "filteredGkCount": 0,
    "filteredOrgCount": 1,
    "filteredPtCount": 0,
    "foundationYear": "2005",
    "gkCountSales": 1,
    "id": "6046155001",
    "maxApartmentCostM2": "34653",
    "maxCostMillion": "1.29",
    "minApartmentCostM2": "34653",
    "minCostMillion": "1.29",
    "name": "ГК ВологдаРегионЛЕС",
    "orgCountAll": 1,
    "orgCountSales": 1,
    "ptCountSales": 0,
    "region": "Вологодская область",
    "regionKey": "142254001",
    "regionPlace": "40",
    "rfPlace": "2609",
    "shareRegionPercent": "0.38",
    "urlId": "gk-vologdaregionles-6046155001"
  },
  {
    "apartmentsCountAll": 66,
    "apartmentsCountSales": 14,
    "buildingVolume": "4312",
    "coefficientRating": "2.47",
    "complexesCountAll": 5,
    "complexesCountSales": 2,
    "filteredApartmentsCount": 14,
    "filteredComplexCount": 2,
    "filteredGkCount": 0,
    "filteredOrgCount": 1,
    "filteredPtCount": 0,
    "foundationYear": "2008",
    "gkCountSales": 2,
    "id": "6299748001",
    "maxApartmentCostM2": "50000",
    "maxCostMillion": "4.91",
    "minApartmentCostM2": "43703",
    "minCostMillion": "1.67",
    "name": "Спецстроймонтаж",
    "orgCountAll": 1,
    "orgCountSales": 1,
    "ptCountSales": 0,
    "rating": "5",
    "region": "Вологодская область",
    "regionKey": "142254001",
    "regionPlace": "41",
    "rfPlace": "2615",
    "shareRegionPercent": "0.37",
    "urlId": "specstrojmontazh-6299748001"
  },
  {
    "apartmentsCountAll": 12,
    "apartmentsCountSales": 3,
    "buildingVolume": "3520",
    "coefficientRating": "2.02",
    "complexesCountAll": 1,
    "complexesCountSales": 1,
    "filteredApartmentsCount": 3,
    "filteredComplexCount": 1,
    "filteredGkCount": 0,
    "filteredOrgCount": 1,
    "filteredPtCount": 0,
    "foundationYear": "2014",
    "gkCountSales": 1,
    "id": "6699349001",
    "maxApartmentCostM2": "50000",
    "maxCostMillion": "4.92",
    "minApartmentCostM2": "43000",
    "minCostMillion": "1.98",
    "name": "СК Домстрой",
    "orgCountAll": 1,
    "orgCountSales": 1,
    "ptCountSales": 0,
    "region": "Вологодская область",
    "regionKey": "142254001",
    "regionPlace": "43",
    "rfPlace": "2743",
    "shareRegionPercent": "0.31",
    "urlId": "stroitelnaja-kompanija-domstroj-6699349001"
  },
  {
    "apartmentsCountAll": 10,
    "apartmentsCountSales": 1,
    "buildingVolume": "3411",
    "coefficientRating": "1.96",
    "complexesCountAll": 1,
    "complexesCountSales": 1,
    "filteredApartmentsCount": 1,
    "filteredComplexCount": 1,
    "filteredGkCount": 0,
    "filteredOrgCount": 1,
    "filteredPtCount": 0,
    "foundationYear": "2012",
    "gkCountSales": 1,
    "id": "7543436001",
    "maxApartmentCostM2": "37000",
    "maxCostMillion": "2.43",
    "minApartmentCostM2": "37000",
    "minCostMillion": "2.43",
    "name": "Стройсектор",
    "orgCountAll": 1,
    "orgCountSales": 1,
    "ptCountSales": 0,
    "region": "Вологодская область",
    "regionKey": "142254001",
    "regionPlace": "45",
    "rfPlace": "2754",
    "shareRegionPercent": "0.3",
    "urlId": "-strojsektor-7543436001"
  },
  {
    "apartmentsCountAll": 19,
    "apartmentsCountSales": 19,
    "buildingVolume": "2572",
    "coefficientRating": "1.48",
    "complexesCountAll": 1,
    "complexesCountSales": 1,
    "filteredApartmentsCount": 19,
    "filteredComplexCount": 1,
    "filteredGkCount": 0,
    "filteredOrgCount": 1,
    "filteredPtCount": 0,
    "foundationYear": "2015",
    "gkCountSales": 1,
    "id": "6066788001",
    "maxApartmentCostM2": "57000",
    "maxCostMillion": "5.33",
    "minApartmentCostM2": "53999",
    "minCostMillion": "3.39",
    "name": "ИНТЕЛЛЕКТ СЕРВИС",
    "orgCountAll": 1,
    "orgCountSales": 1,
    "ptCountSales": 0,
    "region": "Вологодская область",
    "regionKey": "142254001",
    "regionPlace": "47",
    "rfPlace": "2899",
    "shareRegionPercent": "0.22",
    "urlId": "intellekt-servis-6066788001"
  },
  {
    "apartmentsCountAll": 2,
    "apartmentsCountSales": 2,
    "buildingVolume": "2116",
    "coefficientRating": "1.21",
    "complexesCountAll": 2,
    "complexesCountSales": 1,
    "filteredApartmentsCount": 2,
    "filteredComplexCount": 1,
    "filteredGkCount": 0,
    "filteredOrgCount": 1,
    "filteredPtCount": 0,
    "gkCountSales": 1,
    "id": "6263634001",
    "maxApartmentCostM2": "51000",
    "maxCostMillion": "5.81",
    "minApartmentCostM2": "51000",
    "minCostMillion": "4.97",
    "name": "Компания Ардстрой",
    "orgCountAll": 2,
    "orgCountSales": 1,
    "ptCountSales": 0,
    "region": "Вологодская область",
    "regionKey": "142254001",
    "regionPlace": "48",
    "rfPlace": "2988",
    "shareRegionPercent": "0.18",
    "urlId": "kompanija-ardstroj-6263634001"
  },
  {
    "apartmentsCountAll": 30,
    "apartmentsCountSales": 30,
    "buildingVolume": "1843",
    "coefficientRating": "1.06",
    "complexesCountAll": 1,
    "complexesCountSales": 1,
    "filteredApartmentsCount": 30,
    "filteredComplexCount": 1,
    "filteredGkCount": 0,
    "filteredOrgCount": 1,
    "filteredPtCount": 0,
    "foundationYear": "2008",
    "gkCountSales": 1,
    "id": "8761564001",
    "maxApartmentCostM2": "54600",
    "maxCostMillion": "6.02",
    "minApartmentCostM2": "46930",
    "minCostMillion": "0.78",
    "name": "РС ГРОССТРОЙ",
    "orgCountAll": 1,
    "orgCountSales": 1,
    "ptCountSales": 0,
    "region": "Вологодская область",
    "regionKey": "142254001",
    "regionPlace": "50",
    "rfPlace": "3042",
    "shareRegionPercent": "0.16",
    "urlId": "-rs-grosstroj-8761564001"
  },
  {
    "apartmentsCountAll": 25,
    "apartmentsCountSales": 25,
    "buildingVolume": "1761",
    "coefficientRating": "1.01",
    "complexesCountAll": 1,
    "complexesCountSales": 1,
    "filteredApartmentsCount": 25,
    "filteredComplexCount": 1,
    "filteredGkCount": 0,
    "filteredOrgCount": 1,
    "filteredPtCount": 0,
    "foundationYear": "2008",
    "gkCountSales": 1,
    "id": "7775429001",
    "maxApartmentCostM2": "33000",
    "maxCostMillion": "2.22",
    "minApartmentCostM2": "30000",
    "minCostMillion": "1.16",
    "name": "МСК",
    "orgCountAll": 1,
    "orgCountSales": 1,
    "ptCountSales": 0,
    "region": "Вологодская область",
    "regionKey": "142254001",
    "regionPlace": "53",
    "rfPlace": "3064",
    "shareRegionPercent": "0.15",
    "urlId": "-metall-snab-kompanija-7775429001"
  },
  {
    "apartmentsCountAll": 1,
    "apartmentsCountSales": 1,
    "buildingVolume": "1440",
    "coefficientRating": "0.83",
    "complexesCountAll": 2,
    "complexesCountSales": 1,
    "filteredApartmentsCount": 1,
    "filteredComplexCount": 1,
    "filteredGkCount": 0,
    "filteredOrgCount": 1,
    "filteredPtCount": 0,
    "gkCountSales": 1,
    "id": "6267783001",
    "maxApartmentCostM2": "52381",
    "maxCostMillion": "2.2",
    "minApartmentCostM2": "52381",
    "minCostMillion": "2.2",
    "name": "Стройтранссервис",
    "orgCountAll": 3,
    "orgCountSales": 1,
    "ptCountSales": 0,
    "region": "Вологодская область",
    "regionKey": "142254001",
    "regionPlace": "54",
    "rfPlace": "3113",
    "shareRegionPercent": "0.13",
    "urlId": "strojtransservis-6267783001"
  },
  {
    "apartmentsCountAll": 1,
    "apartmentsCountSales": 1,
    "buildingVolume": "1371",
    "coefficientRating": "0.79",
    "complexesCountAll": 6,
    "complexesCountSales": 1,
    "filteredApartmentsCount": 1,
    "filteredComplexCount": 1,
    "filteredGkCount": 0,
    "filteredOrgCount": 1,
    "filteredPtCount": 0,
    "foundationYear": "1997",
    "gkCountSales": 1,
    "id": "4143459001",
    "maxApartmentCostM2": "29000",
    "maxCostMillion": "1.41",
    "minApartmentCostM2": "29000",
    "minCostMillion": "1.41",
    "name": "СК Вытегра",
    "orgCountAll": 1,
    "orgCountSales": 1,
    "ptCountSales": 0,
    "region": "Вологодская область",
    "regionKey": "142254001",
    "regionPlace": "55",
    "rfPlace": "3124",
    "shareRegionPercent": "0.12",
    "urlId": "stroitelnaja-kompanija-vytegra-4143459001"
  },
  {
    "apartmentsCountAll": 14,
    "apartmentsCountSales": 13,
    "buildingVolume": "856",
    "coefficientRating": "0.49",
    "complexesCountAll": 1,
    "complexesCountSales": 1,
    "filteredApartmentsCount": 13,
    "filteredComplexCount": 1,
    "filteredGkCount": 0,
    "filteredOrgCount": 1,
    "filteredPtCount": 0,
    "foundationYear": "2007",
    "gkCountSales": 1,
    "id": "8535214001",
    "maxApartmentCostM2": "60900",
    "maxCostMillion": "6.58",
    "minApartmentCostM2": "52344",
    "minCostMillion": "2.76",
    "name": "НовелДевелопмент",
    "orgCountAll": 1,
    "orgCountSales": 1,
    "ptCountSales": 0,
    "region": "Вологодская область",
    "regionKey": "142254001",
    "regionPlace": "57",
    "rfPlace": "3209",
    "shareRegionPercent": "0.07",
    "urlId": "-noveldevelopment-8535214001"
  },
  {
    "apartmentsCountAll": 185,
    "apartmentsCountSales": 10,
    "complexesCountAll": 4,
    "complexesCountSales": 2,
    "filteredApartmentsCount": 10,
    "filteredComplexCount": 2,
    "filteredGkCount": 0,
    "filteredOrgCount": 3,
    "filteredPtCount": 0,
    "foundationYear": "1993",
    "gkCountSales": 2,
    "id": "1583897001",
    "maxApartmentCostM2": "49855",
    "maxCostMillion": "4.49",
    "minApartmentCostM2": "44900",
    "minCostMillion": "1.6",
    "name": "Холдинг Золотой Ключик",
    "orgCountAll": 4,
    "orgCountSales": 3,
    "ptCountSales": 0,
    "rating": "2",
    "region": "Вологодская область",
    "regionKey": "142254001",
    "urlId": "kholding-zolotoj-kljuchik-1583897001"
  },
  {
    "apartmentsCountAll": 1,
    "apartmentsCountSales": 1,
    "complexesCountAll": 1,
    "complexesCountSales": 1,
    "filteredApartmentsCount": 1,
    "filteredComplexCount": 1,
    "filteredGkCount": 0,
    "filteredOrgCount": 1,
    "filteredPtCount": 0,
    "foundationYear": "2016",
    "gkCountSales": 1,
    "id": "8145950001",
    "maxApartmentCostM2": "65045",
    "maxCostMillion": "4.6",
    "minApartmentCostM2": "65045",
    "minCostMillion": "4.6",
    "name": "СМУ-8",
    "orgCountAll": 1,
    "orgCountSales": 1,
    "ptCountSales": 0,
    "region": "Вологодская область",
    "regionKey": "142254001",
    "urlId": "-smu-8-8145950001"
  },
  {
    "apartmentsCountAll": 2,
    "apartmentsCountSales": 2,
    "complexesCountAll": 4,
    "complexesCountSales": 1,
    "filteredApartmentsCount": 2,
    "filteredComplexCount": 1,
    "filteredGkCount": 0,
    "filteredOrgCount": 1,
    "filteredPtCount": 0,
    "foundationYear": "2014",
    "gkCountSales": 1,
    "id": "5740066001",
    "maxApartmentCostM2": "36296",
    "maxCostMillion": "2.35",
    "minApartmentCostM2": "35075",
    "minCostMillion": "0.98",
    "name": "СК Вологдастрой",
    "orgCountAll": 2,
    "orgCountSales": 1,
    "ptCountSales": 0,
    "rating": "5",
    "region": "Вологодская область",
    "regionKey": "142254001",
    "urlId": "stroitelnaja-kompanija-vologdastroj-5740066001"
  },
  {
    "apartmentsCountAll": 1,
    "apartmentsCountSales": 1,
    "complexesCountAll": 1,
    "complexesCountSales": 1,
    "filteredApartmentsCount": 1,
    "filteredComplexCount": 1,
    "filteredGkCount": 0,
    "filteredOrgCount": 1,
    "filteredPtCount": 0,
    "foundationYear": "2014",
    "gkCountSales": 1,
    "id": "7794018001",
    "maxApartmentCostM2": "52000",
    "maxCostMillion": "4.42",
    "minApartmentCostM2": "52000",
    "minCostMillion": "4.42",
    "name": "СК СЕВЕРНЫЙ ГОРОД",
    "orgCountAll": 1,
    "orgCountSales": 1,
    "ptCountSales": 0,
    "region": "Вологодская область",
    "regionKey": "142254001",
    "urlId": "-stroitelnaja-kompanija-severnyj-gorod-7794018001"
  },
  {
    "apartmentsCountAll": 4,
    "apartmentsCountSales": 4,
    "complexesCountAll": 2,
    "complexesCountSales": 1,
    "filteredApartmentsCount": 4,
    "filteredComplexCount": 1,
    "filteredGkCount": 0,
    "filteredOrgCount": 1,
    "filteredPtCount": 0,
    "foundationYear": "1998",
    "gkCountSales": 1,
    "id": "6279143001",
    "maxApartmentCostM2": "59625",
    "maxCostMillion": "4.88",
    "minApartmentCostM2": "51304",
    "minCostMillion": "2.92",
    "name": "Северный фасад",
    "orgCountAll": 1,
    "orgCountSales": 1,
    "ptCountSales": 0,
    "region": "Вологодская область",
    "regionKey": "142254001",
    "urlId": "severnyj-fasad-6279143001"
  },
  {
    "apartmentsCountAll": 350,
    "apartmentsCountSales": 175,
    "complexesCountAll": 3,
    "complexesCountSales": 2,
    "filteredApartmentsCount": 175,
    "filteredComplexCount": 2,
    "filteredGkCount": 0,
    "filteredOrgCount": 2,
    "filteredPtCount": 0,
    "foundationYear": "2012",
    "gkCountSales": 2,
    "id": "6014916001",
    "maxApartmentCostM2": "40000",
    "maxCostMillion": "4.12",
    "minApartmentCostM2": "35000",
    "minCostMillion": "1.42",
    "name": "ГК СтройТехСервис",
    "orgCountAll": 2,
    "orgCountSales": 2,
    "ptCountSales": 0,
    "rating": "5",
    "region": "Вологодская область",
    "regionKey": "142254001",
    "urlId": "sk-grad-6014916001"
  },
  {
    "apartmentsCountAll": 1,
    "apartmentsCountSales": 1,
    "complexesCountAll": 2,
    "complexesCountSales": 1,
    "filteredApartmentsCount": 1,
    "filteredComplexCount": 1,
    "filteredGkCount": 0,
    "filteredOrgCount": 1,
    "filteredPtCount": 0,
    "foundationYear": "2014",
    "gkCountSales": 1,
    "id": "6026064001",
    "maxApartmentCostM2": "45455",
    "maxCostMillion": "5.0",
    "minApartmentCostM2": "45455",
    "minCostMillion": "5.0",
    "name": "Стройиндустрия-Череповец",
    "orgCountAll": 1,
    "orgCountSales": 1,
    "ptCountSales": 0,
    "region": "Вологодская область",
    "regionKey": "142254001",
    "urlId": "strojindustrija-cherepovec-6026064001"
  },
  {
    "apartmentsCountAll": 8,
    "apartmentsCountSales": 8,
    "complexesCountAll": 2,
    "complexesCountSales": 1,
    "filteredApartmentsCount": 8,
    "filteredComplexCount": 1,
    "filteredGkCount": 0,
    "filteredOrgCount": 1,
    "filteredPtCount": 0,
    "foundationYear": "2008",
    "gkCountSales": 1,
    "id": "6017481001",
    "maxApartmentCostM2": "40000",
    "maxCostMillion": "2.39",
    "minApartmentCostM2": "39000",
    "minCostMillion": "1.05",
    "name": "РегионСпецСтрой",
    "orgCountAll": 1,
    "orgCountSales": 1,
    "ptCountSales": 0,
    "region": "Вологодская область",
    "regionKey": "142254001",
    "urlId": "regionspecstroj-6017481001"
  },
  {
    "apartmentsCountAll": 54,
    "apartmentsCountSales": 54,
    "complexesCountAll": 1,
    "complexesCountSales": 1,
    "filteredApartmentsCount": 54,
    "filteredComplexCount": 1,
    "filteredGkCount": 0,
    "filteredOrgCount": 1,
    "filteredPtCount": 0,
    "foundationYear": "2012",
    "gkCountSales": 1,
    "id": "6025144001",
    "maxApartmentCostM2": "38002",
    "maxCostMillion": "3.34",
    "minApartmentCostM2": "32973",
    "minCostMillion": "1.71",
    "name": "Профит",
    "orgCountAll": 1,
    "orgCountSales": 1,
    "ptCountSales": 0,
    "rating": "3.5",
    "region": "Вологодская область",
    "regionKey": "142254001",
    "urlId": "profit-6025144001"
  }
]
