[{"apartmentsCountAll":"19","apartmentsCountSales":"4","buildingVolume":"106567","coefficientRating":"100","complexesCountAll":"3","complexesCountSales":"2","filteredApartmentsCount":"4","filteredComplexCount":"2","filteredGkCount":"0","filteredOrgCount":"2","filteredPtCount":"0","foundationYear":"2015","gkCountSales":"2","id":"5599108001","maxApartmentCostM2":"59022","maxCostMillion":"2.86","minApartmentCostM2":"48814","minCostMillion":"1.4","name":"ДК Прогресс","orgCountAll":"2","orgCountSales":"2","ptCountSales":"0","rating":"4","region":"Астраханская область","regionKey":"144115001","regionPlace":"1","rfPlace":"246","shareRegionPercent":"28.51","urlId":"developerskaja-kompanija-tajger-5599108001"},{"apartmentsCountAll":"7","apartmentsCountSales":"4","buildingVolume":"55611","coefficientRating":"52.49","complexesCountAll":"3","complexesCountSales":"1","filteredApartmentsCount":"4","filteredComplexCount":"1","filteredGkCount":"0","filteredOrgCount":"1","filteredPtCount":"0","foundationYear":"2007","gkCountSales":"1","id":"4296089001","maxApartmentCostM2":"56957","maxCostMillion":"5.24","minApartmentCostM2":"54619","minCostMillion":"3.2","name":"ГК Сити Групп","orgCountAll":"2","orgCountSales":"1","ptCountSales":"0","rating":"4","region":"Астраханская область","regionKey":"144115001","regionPlace":"2","rfPlace":"490","shareRegionPercent":"15.49","urlId":"gruppa-kompanij-siti-grupp-4296089001"},{"apartmentsCountAll":"10","apartmentsCountSales":"7","buildingVolume":"34091","coefficientRating":"32.18","complexesCountAll":"1","complexesCountSales":"1","filteredApartmentsCount":"7","filteredComplexCount":"1","filteredGkCount":"0","filteredOrgCount":"1","filteredPtCount":"0","foundationYear":"2004","gkCountSales":"1","id":"5593518001","maxApartmentCostM2":"52000","maxCostMillion":"7.05","minApartmentCostM2":"44000","minCostMillion":"2.38","name":"ПКФ Нижневолжская строительная компания","orgCountAll":"1","orgCountSales":"1","ptCountSales":"0","rating":"2","region":"Астраханская область","regionKey":"144115001","regionPlace":"3","rfPlace":"757","shareRegionPercent":"9.49","urlId":"proizvodstvenno-kommercheskaja-firma-nizhnevolzhskaja-stroitelnaja-kompanija-5593518001"},{"apartmentsCountAll":"492","apartmentsCountSales":"469","buildingVolume":"33757","coefficientRating":"31.86","complexesCountAll":"1","complexesCountSales":"1","filteredApartmentsCount":"469","filteredComplexCount":"1","filteredGkCount":"0","filteredOrgCount":"1","filteredPtCount":"0","foundationYear":"2005","gkCountSales":"1","id":"5593755001","maxApartmentCostM2":"64050","maxCostMillion":"8.7","minApartmentCostM2":"53951","minCostMillion":"2.64","name":"Городской Курорт Астрахани","orgCountAll":"1","orgCountSales":"1","ptCountSales":"0","rating":"0.5","region":"Астраханская область","regionKey":"144115001","regionPlace":"4","rfPlace":"763","shareRegionPercent":"9.4","urlId":"gorodskoj-kurort-astrakhani-5593755001"},{"apartmentsCountAll":"173","apartmentsCountSales":"173","buildingVolume":"15051","coefficientRating":"14.21","complexesCountAll":"1","complexesCountSales":"1","filteredApartmentsCount":"173","filteredComplexCount":"1","filteredGkCount":"0","filteredOrgCount":"1","filteredPtCount":"0","foundationYear":"2002","gkCountSales":"1","id":"9654514001","maxApartmentCostM2":"54600","maxCostMillion":"4.57","minApartmentCostM2":"48412","minCostMillion":"2.23","name":"Буран","orgCountAll":"1","orgCountSales":"1","ptCountSales":"0","region":"Астраханская область","regionKey":"144115001","regionPlace":"6","rfPlace":"1387","shareRegionPercent":"4.19","urlId":"-buran-9654514001"},{"apartmentsCountAll":"2","apartmentsCountSales":"2","buildingVolume":"14764","coefficientRating":"13.94","complexesCountAll":"2","complexesCountSales":"1","filteredApartmentsCount":"2","filteredComplexCount":"1","filteredGkCount":"0","filteredOrgCount":"1","filteredPtCount":"0","foundationYear":"2005","gkCountSales":"1","id":"8715786001","maxApartmentCostM2":"42000","maxCostMillion":"2.97","minApartmentCostM2":"41992","minCostMillion":"2.04","name":"Регионкапстрой","orgCountAll":"1","orgCountSales":"1","ptCountSales":"0","rating":"0.5","region":"Астраханская область","regionKey":"144115001","regionPlace":"7","rfPlace":"1401","shareRegionPercent":"4.11","urlId":"-regionkapstroj-8715786001"},{"apartmentsCountAll":"6","apartmentsCountSales":"6","buildingVolume":"9852","coefficientRating":"9.3","complexesCountAll":"2","complexesCountSales":"1","filteredApartmentsCount":"6","filteredComplexCount":"1","filteredGkCount":"0","filteredOrgCount":"1","filteredPtCount":"0","foundationYear":"2015","gkCountSales":"1","id":"11401897001","maxApartmentCostM2":"38000","maxCostMillion":"3.44","minApartmentCostM2":"38000","minCostMillion":"1.5","name":"ВКРК","orgCountAll":"1","orgCountSales":"1","ptCountSales":"0","region":"Астраханская область","regionKey":"144115001","regionPlace":"9","rfPlace":"1812","shareRegionPercent":"2.74","urlId":"11401897001"},{"apartmentsCountAll":"8","apartmentsCountSales":"5","buildingVolume":"9497","coefficientRating":"8.91","complexesCountAll":"5","complexesCountSales":"3","filteredApartmentsCount":"5","filteredComplexCount":"3","filteredGkCount":"0","filteredOrgCount":"1","filteredPtCount":"0","foundationYear":"2005","gkCountSales":"3","id":"5392758001","maxApartmentCostM2":"37000","maxCostMillion":"2.75","minApartmentCostM2":"30000","minCostMillion":"0.76","name":"АДС-Инвест","orgCountAll":"1","orgCountSales":"1","ptCountSales":"0","rating":"2","region":"Астраханская область","regionKey":"144115001","regionPlace":"10","rfPlace":"1864","shareRegionPercent":"2.54","urlId":"astdomstroj-invest-5392758001"},{"apartmentsCountAll":"3","apartmentsCountSales":"3","buildingVolume":"8477","coefficientRating":"8","complexesCountAll":"3","complexesCountSales":"2","filteredApartmentsCount":"3","filteredComplexCount":"2","filteredGkCount":"0","filteredOrgCount":"1","filteredPtCount":"0","foundationYear":"2001","gkCountSales":"2","id":"6261544001","maxApartmentCostM2":"60000","maxCostMillion":"4.32","minApartmentCostM2":"48000","minCostMillion":"4.31","name":"СК Инвест-Строй","orgCountAll":"1","orgCountSales":"1","ptCountSales":"0","rating":"1.5","region":"Астраханская область","regionKey":"144115001","regionPlace":"11","rfPlace":"1962","shareRegionPercent":"2.36","urlId":"stroitelnaja-kompanija-invest-stroj-6261544001"},{"apartmentsCountAll":"4","apartmentsCountSales":"3","buildingVolume":"6784","coefficientRating":"6.4","complexesCountAll":"1","complexesCountSales":"1","filteredApartmentsCount":"3","filteredComplexCount":"1","filteredGkCount":"0","filteredOrgCount":"1","filteredPtCount":"0","foundationYear":"2002","gkCountSales":"1","id":"5633566001","maxApartmentCostM2":"52083","maxCostMillion":"2.5","minApartmentCostM2":"50000","minCostMillion":"2.4","name":"Управляющая строительная компания Стройкомплекс","orgCountAll":"1","orgCountSales":"1","ptCountSales":"0","rating":"3","region":"Астраханская область","regionKey":"144115001","regionPlace":"12","rfPlace":"2192","shareRegionPercent":"1.89","urlId":"upravljajushhaja-stroitelnaja-kompanija-strojkompleks-5633566001"},{"apartmentsCountAll":"12","apartmentsCountSales":"7","buildingVolume":"6647","coefficientRating":"6.27","complexesCountAll":"5","complexesCountSales":"2","filteredApartmentsCount":"7","filteredComplexCount":"2","filteredGkCount":"0","filteredOrgCount":"1","filteredPtCount":"0","foundationYear":"1999","gkCountSales":"2","id":"5482734001","maxApartmentCostM2":"36304","maxCostMillion":"3.07","minApartmentCostM2":"30000","minCostMillion":"1.33","name":"АДСК","orgCountAll":"1","orgCountSales":"1","ptCountSales":"0","rating":"1","region":"Астраханская область","regionKey":"144115001","regionPlace":"13","rfPlace":"2207","shareRegionPercent":"1.85","urlId":"astrakhanskij-domostroitelnyj-kombinat-5482734001"},{"apartmentsCountAll":"37","apartmentsCountSales":"32","buildingVolume":"6374","coefficientRating":"5.98","complexesCountAll":"1","complexesCountSales":"1","filteredApartmentsCount":"32","filteredComplexCount":"1","filteredGkCount":"0","filteredOrgCount":"1","filteredPtCount":"0","foundationYear":"1995","gkCountSales":"1","id":"1459022001","maxApartmentCostM2":"53025","maxCostMillion":"3.64","minApartmentCostM2":"49490","minCostMillion":"1.97","name":"ГК Девелопмент-Юг","orgCountAll":"1","orgCountSales":"1","ptCountSales":"0","rating":"4","region":"Астраханская область","regionKey":"144115001","regionPlace":"15","rfPlace":"50","shareRegionPercent":"1.71","urlId":"gruppa-kompanij-development-jug-1459022001"},{"apartmentsCountAll":"49","apartmentsCountSales":"42","buildingVolume":"5128","coefficientRating":"4.84","complexesCountAll":"3","complexesCountSales":"1","filteredApartmentsCount":"42","filteredComplexCount":"1","filteredGkCount":"0","filteredOrgCount":"1","filteredPtCount":"0","foundationYear":"1997","gkCountSales":"1","id":"5597235001","maxApartmentCostM2":"41000","maxCostMillion":"3.32","minApartmentCostM2":"37000","minCostMillion":"2.17","name":"ЛютанСтройСервис","orgCountAll":"1","orgCountSales":"1","ptCountSales":"0","rating":"2","region":"Астраханская область","regionKey":"144115001","regionPlace":"15","rfPlace":"2477","shareRegionPercent":"1.43","urlId":"ljutanstrojservis-5597235001"},{"apartmentsCountAll":"2","apartmentsCountSales":"2","buildingVolume":"2806","coefficientRating":"2.65","complexesCountAll":"1","complexesCountSales":"1","filteredApartmentsCount":"2","filteredComplexCount":"1","filteredGkCount":"0","filteredOrgCount":"1","filteredPtCount":"0","foundationYear":"2017","gkCountSales":"1","id":"9652996001","maxApartmentCostM2":"42000","maxCostMillion":"2.56","minApartmentCostM2":"42000","minCostMillion":"1.81","name":"СК Квартал","orgCountAll":"1","orgCountSales":"1","ptCountSales":"0","region":"Астраханская область","regionKey":"144115001","regionPlace":"16","rfPlace":"2858","shareRegionPercent":"0.78","urlId":"-stroitelnaja-kompanija-kvartal-9652996001"},{"apartmentsCountAll":"5","apartmentsCountSales":"5","buildingVolume":"2634","coefficientRating":"2.49","complexesCountAll":"2","complexesCountSales":"1","filteredApartmentsCount":"5","filteredComplexCount":"1","filteredGkCount":"0","filteredOrgCount":"1","filteredPtCount":"0","gkCountSales":"1","id":"8151590001","maxApartmentCostM2":"59000","maxCostMillion":"5.86","minApartmentCostM2":"58000","minCostMillion":"4.55","name":"ИФК Астрстройинвест","orgCountAll":"1","orgCountSales":"1","ptCountSales":"0","region":"Астраханская область","regionKey":"144115001","regionPlace":"17","rfPlace":"2888","shareRegionPercent":"0.73","urlId":"-ifk-astrstrojinvest-8151590001"},{"apartmentsCountAll":"3","apartmentsCountSales":"3","buildingVolume":"2430","coefficientRating":"2.29","complexesCountAll":"1","complexesCountSales":"1","filteredApartmentsCount":"3","filteredComplexCount":"1","filteredGkCount":"0","filteredOrgCount":"1","filteredPtCount":"0","foundationYear":"2010","gkCountSales":"1","id":"5504309001","maxApartmentCostM2":"47011","maxCostMillion":"2.07","minApartmentCostM2":"45844","minCostMillion":"1.73","name":"Регион-Строй","orgCountAll":"1","orgCountSales":"1","ptCountSales":"0","region":"Астраханская область","regionKey":"144115001","regionPlace":"18","rfPlace":"2924","shareRegionPercent":"0.68","urlId":"region-stroj-5504309001"},{"apartmentsCountAll":"1","apartmentsCountSales":"1","complexesCountAll":"2","complexesCountSales":"1","filteredApartmentsCount":"1","filteredComplexCount":"1","filteredGkCount":"0","filteredOrgCount":"1","filteredPtCount":"0","foundationYear":"2008","gkCountSales":"1","id":"5593908001","maxApartmentCostM2":"38848","maxCostMillion":"2.09","minApartmentCostM2":"38848","minCostMillion":"2.09","name":"Капстрой Инжиниринг","orgCountAll":"1","orgCountSales":"1","ptCountSales":"0","region":"Астраханская область","regionKey":"144115001","urlId":"kapstroj-inzhiniring-5593908001"},{"apartmentsCountAll":"1","apartmentsCountSales":"1","complexesCountAll":"2","complexesCountSales":"1","filteredApartmentsCount":"1","filteredComplexCount":"1","filteredGkCount":"0","filteredOrgCount":"1","filteredPtCount":"0","foundationYear":"1998","gkCountSales":"1","id":"5593379001","maxApartmentCostM2":"46000","maxCostMillion":"1.83","minApartmentCostM2":"46000","minCostMillion":"1.83","name":"СМУ №3","orgCountAll":"2","orgCountSales":"1","ptCountSales":"0","rating":"1.5","region":"Астраханская область","regionKey":"144115001","urlId":"stroitelno-montazhnoe-upravlenie-№3-5593379001"}]