[{"apartmentsCountAll":12,"apartmentsCountSales":12,"buildingVolume":"73331","coefficientRating":"100","complexesCountAll":1,"complexesCountSales":1,"filteredApartmentsCount":12,"filteredComplexCount":1,"filteredGkCount":0,"filteredOrgCount":1,"filteredPtCount":0,"foundationYear":"1992","gkCountSales":1,"id":"6104156001","maxApartmentCostM2":"84008","maxCostMillion":"5.12","minApartmentCostM2":"59529","minCostMillion":"1.95","name":"ГК ЭНКА","orgCountAll":1,"orgCountSales":1,"ptCountSales":0,"rating":"2.5","region":"Хабаровский край","regionKey":"145501001","regionPlace":"1","rfPlace":"373","shareRegionPercent":"14.35","urlId":"gruppa-kompanij-enka-6104156001"},{"apartmentsCountAll":1,"apartmentsCountSales":1,"buildingVolume":"56179","coefficientRating":"76.61","complexesCountAll":1,"complexesCountSales":1,"filteredApartmentsCount":1,"filteredComplexCount":1,"filteredGkCount":0,"filteredOrgCount":1,"filteredPtCount":0,"foundationYear":"2007","gkCountSales":1,"id":"773868001","maxApartmentCostM2":"50850","maxCostMillion":"2.24","minApartmentCostM2":"50850","minCostMillion":"2.24","name":"ГК Амурские зори","orgCountAll":1,"orgCountSales":1,"ptCountSales":0,"rating":"0.5","region":"Хабаровский край","regionKey":"145501001","regionPlace":"2","rfPlace":"485","shareRegionPercent":"11.13","urlId":"gruppa-kompanij-amurskie-zori-773868001"},{"apartmentsCountAll":6,"apartmentsCountSales":2,"buildingVolume":"37685","coefficientRating":"51.39","complexesCountAll":6,"complexesCountSales":1,"filteredApartmentsCount":2,"filteredComplexCount":1,"filteredGkCount":0,"filteredOrgCount":1,"filteredPtCount":0,"foundationYear":"2001","gkCountSales":1,"id":"706107001","maxApartmentCostM2":"71429","maxCostMillion":"3.0","minApartmentCostM2":"70000","minCostMillion":"2.1","name":"УИП г. Хабаровска","orgCountAll":3,"orgCountSales":1,"ptCountSales":0,"rating":"3.5","region":"Хабаровский край","regionKey":"145501001","regionPlace":"3","rfPlace":"693","shareRegionPercent":"7.47","urlId":"upravlenie-investicionnykh-programm-goroda-khabarovska-706107001"},{"apartmentsCountAll":3,"apartmentsCountSales":2,"buildingVolume":"37031","coefficientRating":"50.5","complexesCountAll":1,"complexesCountSales":1,"filteredApartmentsCount":2,"filteredComplexCount":1,"filteredGkCount":0,"filteredOrgCount":1,"filteredPtCount":0,"foundationYear":"2012","gkCountSales":1,"id":"5226696001","maxApartmentCostM2":"62500","maxCostMillion":"3.2","minApartmentCostM2":"55000","minCostMillion":"2.04","name":"ГК СтройМеталл","orgCountAll":3,"orgCountSales":1,"ptCountSales":0,"region":"Хабаровский край","regionKey":"145501001","regionPlace":"4","rfPlace":"699","shareRegionPercent":"7.34","urlId":"gruppa-kompanij-strojmetall-5226696001"},{"apartmentsCountAll":13,"apartmentsCountSales":2,"buildingVolume":"27076","coefficientRating":"36.92","complexesCountAll":4,"complexesCountSales":1,"filteredApartmentsCount":2,"filteredComplexCount":1,"filteredGkCount":0,"filteredOrgCount":1,"filteredPtCount":0,"foundationYear":"1951","gkCountSales":1,"id":"5824042001","maxApartmentCostM2":"75000","maxCostMillion":"4.6","minApartmentCostM2":"73000","minCostMillion":"3.15","name":"ГВСУ №6","orgCountAll":1,"orgCountSales":1,"ptCountSales":0,"rating":"0","region":"Хабаровский край","regionKey":"145501001","regionPlace":"5","rfPlace":"905","shareRegionPercent":"5.36","urlId":"glavnoe-voenno-stroitelnoe-upravlenie-№6-5824042001"},{"apartmentsCountAll":10,"apartmentsCountSales":8,"buildingVolume":"21207","coefficientRating":"28.92","complexesCountAll":2,"complexesCountSales":2,"filteredApartmentsCount":8,"filteredComplexCount":2,"filteredGkCount":0,"filteredOrgCount":2,"filteredPtCount":0,"foundationYear":"2012","gkCountSales":2,"id":"5230655001","maxApartmentCostM2":"78000","maxCostMillion":"3.82","minApartmentCostM2":"72000","minCostMillion":"2.77","name":"ГК БАСК","orgCountAll":2,"orgCountSales":2,"ptCountSales":0,"rating":"1.5","region":"Хабаровский край","regionKey":"145501001","regionPlace":"6","rfPlace":"1069","shareRegionPercent":"4.15","urlId":"gruppa-kompanij-bask-5230655001"},{"apartmentsCountAll":4,"apartmentsCountSales":4,"buildingVolume":"18235","coefficientRating":"24.87","complexesCountAll":4,"complexesCountSales":3,"filteredApartmentsCount":4,"filteredComplexCount":3,"filteredGkCount":0,"filteredOrgCount":3,"filteredPtCount":0,"foundationYear":"1907","gkCountSales":3,"id":"4909750001","maxApartmentCostM2":"68800","maxCostMillion":"3.1","minApartmentCostM2":"45000","minCostMillion":"1.3","name":"ГК ККК","orgCountAll":4,"orgCountSales":3,"ptCountSales":0,"region":"Хабаровский край","regionKey":"145501001","regionPlace":"8","rfPlace":"1217","shareRegionPercent":"3.61","urlId":"gruppa-kompanij-korfovskij-kamennyj-karer-4909750001"},{"apartmentsCountAll":6,"apartmentsCountSales":6,"buildingVolume":"15559","coefficientRating":"21.22","complexesCountAll":1,"complexesCountSales":1,"filteredApartmentsCount":6,"filteredComplexCount":1,"filteredGkCount":0,"filteredOrgCount":1,"filteredPtCount":0,"foundationYear":"2004","gkCountSales":1,"id":"5904592001","maxApartmentCostM2":"37931","maxCostMillion":"2.2","minApartmentCostM2":"33333","minCostMillion":"1.4","name":"Застройщик-ДВ","orgCountAll":1,"orgCountSales":1,"ptCountSales":0,"rating":"0.5","region":"Хабаровский край","regionKey":"145501001","regionPlace":"9","rfPlace":"1354","shareRegionPercent":"3.08","urlId":"zastrojshhik-dv-5904592001"},{"apartmentsCountAll":3,"apartmentsCountSales":3,"buildingVolume":"14623","coefficientRating":"19.94","complexesCountAll":2,"complexesCountSales":1,"filteredApartmentsCount":3,"filteredComplexCount":1,"filteredGkCount":0,"filteredOrgCount":1,"filteredPtCount":0,"foundationYear":"2014","gkCountSales":1,"id":"6077106001","maxApartmentCostM2":"51900","maxCostMillion":"3.55","minApartmentCostM2":"51250","minCostMillion":"1.85","name":"Русинмонолитстрой","orgCountAll":3,"orgCountSales":1,"ptCountSales":0,"region":"Хабаровский край","regionKey":"145501001","regionPlace":"10","rfPlace":"1412","shareRegionPercent":"2.9","urlId":"rosinmonolitstroj-6077106001"},{"apartmentsCountAll":6,"apartmentsCountSales":6,"buildingVolume":"14007","coefficientRating":"19.1","complexesCountAll":1,"complexesCountSales":1,"filteredApartmentsCount":6,"filteredComplexCount":1,"filteredGkCount":0,"filteredOrgCount":1,"filteredPtCount":0,"foundationYear":"2005","gkCountSales":1,"id":"6612295001","maxApartmentCostM2":"65000","maxCostMillion":"13.5","minApartmentCostM2":"65000","minCostMillion":"2.99","name":"СамСтрой","orgCountAll":1,"orgCountSales":1,"ptCountSales":0,"region":"Хабаровский край","regionKey":"145501001","regionPlace":"11","rfPlace":"1443","shareRegionPercent":"2.78","urlId":"samstroj-6612295001"},{"apartmentsCountAll":160,"apartmentsCountSales":81,"buildingVolume":"13339","coefficientRating":"18.19","complexesCountAll":5,"complexesCountSales":2,"filteredApartmentsCount":81,"filteredComplexCount":2,"filteredGkCount":0,"filteredOrgCount":1,"filteredPtCount":0,"foundationYear":"2008","gkCountSales":2,"id":"5987101001","maxApartmentCostM2":"80100","maxCostMillion":"7.11","minApartmentCostM2":"61750","minCostMillion":"1.84","name":"Фонд Жилищного строительства","orgCountAll":1,"orgCountSales":1,"ptCountSales":0,"rating":"1.5","region":"Хабаровский край","regionKey":"145501001","regionPlace":"13","rfPlace":"1499","shareRegionPercent":"2.61","urlId":"fond-zhilishhnogo-stroitelstva-5987101001"},{"apartmentsCountAll":1,"apartmentsCountSales":1,"buildingVolume":"11438","coefficientRating":"15.6","complexesCountAll":1,"complexesCountSales":1,"filteredApartmentsCount":1,"filteredComplexCount":1,"filteredGkCount":0,"filteredOrgCount":1,"filteredPtCount":0,"foundationYear":"2010","gkCountSales":1,"id":"6012237001","maxApartmentCostM2":"125000","maxCostMillion":"5.13","minApartmentCostM2":"125000","minCostMillion":"5.13","name":"Гранд-ДВ","orgCountAll":1,"orgCountSales":1,"ptCountSales":0,"region":"Хабаровский край","regionKey":"145501001","regionPlace":"13","rfPlace":"1639","shareRegionPercent":"2.27","urlId":"grand-dv-6012237001"},{"apartmentsCountAll":2,"apartmentsCountSales":1,"buildingVolume":"11277","coefficientRating":"15.38","complexesCountAll":1,"complexesCountSales":1,"filteredApartmentsCount":1,"filteredComplexCount":1,"filteredGkCount":0,"filteredOrgCount":1,"filteredPtCount":0,"foundationYear":"2012","gkCountSales":1,"id":"5220584001","maxApartmentCostM2":"85000","maxCostMillion":"8.07","minApartmentCostM2":"85000","minCostMillion":"8.07","name":"ГК Да! Девелопмент","orgCountAll":1,"orgCountSales":1,"ptCountSales":0,"region":"Хабаровский край","regionKey":"145501001","regionPlace":"16","rfPlace":"1663","shareRegionPercent":"2.21","urlId":"gruppa-kompanij-da!-development-5220584001"},{"apartmentsCountAll":14,"apartmentsCountSales":12,"buildingVolume":"11024","coefficientRating":"15.03","complexesCountAll":3,"complexesCountSales":3,"filteredApartmentsCount":12,"filteredComplexCount":3,"filteredGkCount":0,"filteredOrgCount":2,"filteredPtCount":0,"foundationYear":"2002","gkCountSales":0,"id":"6110097001","maxApartmentCostM2":"85455","maxCostMillion":"18.8","minApartmentCostM2":"82000","minCostMillion":"7.95","name":"СК Академресурс","orgCountAll":2,"orgCountSales":2,"ptCountSales":3,"region":"Хабаровский край","regionKey":"145501001","regionPlace":"16","rfPlace":"1677","shareRegionPercent":"2.18","urlId":"stroitelnaja-kompanija-akademresurs-6110097001"},{"apartmentsCountAll":1,"apartmentsCountSales":1,"buildingVolume":"9290","coefficientRating":"12.67","complexesCountAll":1,"complexesCountSales":1,"filteredApartmentsCount":1,"filteredComplexCount":1,"filteredGkCount":0,"filteredOrgCount":1,"filteredPtCount":0,"foundationYear":"2014","gkCountSales":1,"id":"6028394001","maxApartmentCostM2":"40323","maxCostMillion":"2.5","minApartmentCostM2":"40323","minCostMillion":"2.5","name":"Первый Семейный Комплекс","orgCountAll":2,"orgCountSales":1,"ptCountSales":0,"rating":"1.5","region":"Хабаровский край","regionKey":"145501001","regionPlace":"17","rfPlace":"1876","shareRegionPercent":"1.84","urlId":"pervyj-semejnyj-kompleks-6028394001"},{"apartmentsCountAll":4,"apartmentsCountSales":4,"buildingVolume":"8938","coefficientRating":"12.19","complexesCountAll":5,"complexesCountSales":2,"filteredApartmentsCount":4,"filteredComplexCount":2,"filteredGkCount":0,"filteredOrgCount":2,"filteredPtCount":0,"foundationYear":"2009","gkCountSales":2,"id":"5179249001","maxApartmentCostM2":"85000","maxCostMillion":"4.39","minApartmentCostM2":"67900","minCostMillion":"2.8","name":"Компания КЕТОМ","orgCountAll":4,"orgCountSales":2,"ptCountSales":0,"region":"Хабаровский край","regionKey":"145501001","regionPlace":"18","rfPlace":"1908","shareRegionPercent":"1.77","urlId":"kompanija-ketom-5179249001"},{"apartmentsCountAll":6,"apartmentsCountSales":5,"buildingVolume":"7702","coefficientRating":"10.5","complexesCountAll":2,"complexesCountSales":1,"filteredApartmentsCount":5,"filteredComplexCount":1,"filteredGkCount":0,"filteredOrgCount":1,"filteredPtCount":0,"foundationYear":"2000","gkCountSales":1,"id":"6047625001","maxApartmentCostM2":"74769","maxCostMillion":"2.43","minApartmentCostM2":"69617","minCostMillion":"1.4","name":"Ладный дом","orgCountAll":1,"orgCountSales":1,"ptCountSales":0,"region":"Хабаровский край","regionKey":"145501001","regionPlace":"19","rfPlace":"2057","shareRegionPercent":"1.53","urlId":"ladnyj-dom-6047625001"},{"apartmentsCountAll":29,"apartmentsCountSales":12,"buildingVolume":"7274","coefficientRating":"9.92","complexesCountAll":2,"complexesCountSales":1,"filteredApartmentsCount":12,"filteredComplexCount":1,"filteredGkCount":0,"filteredOrgCount":1,"filteredPtCount":0,"foundationYear":"2006","gkCountSales":1,"id":"5475213001","maxApartmentCostM2":"115000","maxCostMillion":"8.73","minApartmentCostM2":"100000","minCostMillion":"4.37","name":"ГК Архстрой","orgCountAll":1,"orgCountSales":1,"ptCountSales":0,"rating":"2","region":"Хабаровский край","regionKey":"145501001","regionPlace":"20","rfPlace":"2121","shareRegionPercent":"1.44","urlId":"gruppa-kompanij-arkhstroj-5475213001"},{"apartmentsCountAll":1,"apartmentsCountSales":1,"buildingVolume":"6801","coefficientRating":"9.27","complexesCountAll":1,"complexesCountSales":1,"filteredApartmentsCount":1,"filteredComplexCount":1,"filteredGkCount":0,"filteredOrgCount":1,"filteredPtCount":0,"foundationYear":"2004","gkCountSales":1,"id":"6116674001","maxApartmentCostM2":"55000","maxCostMillion":"2.2","minApartmentCostM2":"55000","minCostMillion":"2.2","name":"ИКАС","orgCountAll":1,"orgCountSales":1,"ptCountSales":0,"region":"Хабаровский край","regionKey":"145501001","regionPlace":"21","rfPlace":"2190","shareRegionPercent":"1.35","urlId":"inzhenerno-konsaltingovoe-agentstvo-strojekspertiza-6116674001"},{"apartmentsCountAll":2,"apartmentsCountSales":1,"buildingVolume":"5600","coefficientRating":"7.64","complexesCountAll":1,"complexesCountSales":1,"filteredApartmentsCount":1,"filteredComplexCount":1,"filteredGkCount":0,"filteredOrgCount":1,"filteredPtCount":0,"gkCountSales":1,"id":"9843425001","maxApartmentCostM2":"50000","maxCostMillion":"2.5","minApartmentCostM2":"50000","minCostMillion":"2.5","name":"Терраса ЛОФТ","orgCountAll":2,"orgCountSales":1,"ptCountSales":0,"region":"Хабаровский край","regionKey":"145501001","regionPlace":"25","rfPlace":"2396","shareRegionPercent":"1.11","urlId":"-terrasa-loft-9843425001"},{"apartmentsCountAll":2,"apartmentsCountSales":2,"buildingVolume":"5140","coefficientRating":"7.01","complexesCountAll":1,"complexesCountSales":1,"filteredApartmentsCount":2,"filteredComplexCount":1,"filteredGkCount":0,"filteredOrgCount":1,"filteredPtCount":0,"foundationYear":"2009","gkCountSales":1,"id":"11003406001","maxApartmentCostM2":"63000","maxCostMillion":"2.63","minApartmentCostM2":"63000","minCostMillion":"2.34","name":"ГК Квадрат 27","orgCountAll":1,"orgCountSales":1,"ptCountSales":0,"region":"Хабаровский край","regionKey":"145501001","regionPlace":"26","rfPlace":"2475","shareRegionPercent":"1.02","urlId":"-gruppa-kompanij-kvadrat-27-11003406001"},{"apartmentsCountAll":4,"apartmentsCountSales":4,"buildingVolume":"3846","coefficientRating":"5.24","complexesCountAll":1,"complexesCountSales":1,"filteredApartmentsCount":4,"filteredComplexCount":1,"filteredGkCount":0,"filteredOrgCount":1,"filteredPtCount":0,"foundationYear":"2014","gkCountSales":1,"id":"7451793001","maxApartmentCostM2":"56500","maxCostMillion":"3.45","minApartmentCostM2":"55000","minCostMillion":"2.17","name":"СК ДоМострой","orgCountAll":1,"orgCountSales":1,"ptCountSales":0,"region":"Хабаровский край","regionKey":"145501001","regionPlace":"28","rfPlace":"2680","shareRegionPercent":"0.76","urlId":"-stroitelnaja-kompanija-domostroj-7451793001"},{"apartmentsCountAll":12,"apartmentsCountSales":7,"buildingVolume":"3800","coefficientRating":"5.18","complexesCountAll":2,"complexesCountSales":2,"filteredApartmentsCount":7,"filteredComplexCount":2,"filteredGkCount":0,"filteredOrgCount":2,"filteredPtCount":0,"foundationYear":"2006","gkCountSales":2,"id":"6107275001","maxApartmentCostM2":"67000","maxCostMillion":"5.12","minApartmentCostM2":"50000","minCostMillion":"1.51","name":"СК Эверест","orgCountAll":2,"orgCountSales":2,"ptCountSales":0,"region":"Хабаровский край","regionKey":"145501001","regionPlace":"29","rfPlace":"2687","shareRegionPercent":"0.75","urlId":"stroitelnaja-kompanija-everest-6107275001"},{"apartmentsCountAll":3,"apartmentsCountSales":3,"buildingVolume":"3524","coefficientRating":"4.81","complexesCountAll":2,"complexesCountSales":1,"filteredApartmentsCount":3,"filteredComplexCount":1,"filteredGkCount":0,"filteredOrgCount":1,"filteredPtCount":0,"foundationYear":"2007","gkCountSales":1,"id":"6059544001","maxApartmentCostM2":"53396","maxCostMillion":"2.83","minApartmentCostM2":"51944","minCostMillion":"1.77","name":"Зодчий","orgCountAll":1,"orgCountSales":1,"ptCountSales":0,"region":"Хабаровский край","regionKey":"145501001","regionPlace":"31","rfPlace":"2742","shareRegionPercent":"0.7","urlId":"zodchij-6059544001"},{"apartmentsCountAll":1,"apartmentsCountSales":1,"buildingVolume":"2692","coefficientRating":"3.67","complexesCountAll":1,"complexesCountSales":1,"filteredApartmentsCount":1,"filteredComplexCount":1,"filteredGkCount":0,"filteredOrgCount":1,"filteredPtCount":0,"gkCountSales":1,"id":"7691109001","maxApartmentCostM2":"75000","maxCostMillion":"3.92","minApartmentCostM2":"75000","minCostMillion":"3.92","name":"Прайд-ДВ","orgCountAll":1,"orgCountSales":1,"ptCountSales":0,"region":"Хабаровский край","regionKey":"145501001","regionPlace":"33","rfPlace":"2881","shareRegionPercent":"0.53","urlId":"-prajd-dv-7691109001"},{"apartmentsCountAll":16,"apartmentsCountSales":16,"buildingVolume":"2135","coefficientRating":"2.91","complexesCountAll":4,"complexesCountSales":2,"filteredApartmentsCount":16,"filteredComplexCount":2,"filteredGkCount":0,"filteredOrgCount":1,"filteredPtCount":0,"foundationYear":"2011","gkCountSales":2,"id":"6024088001","maxApartmentCostM2":"93376","maxCostMillion":"22.7","minApartmentCostM2":"57410","minCostMillion":"2.67","name":"ИСК Реал Строй","orgCountAll":1,"orgCountSales":1,"ptCountSales":0,"rating":"5","region":"Хабаровский край","regionKey":"145501001","regionPlace":"37","rfPlace":"2984","shareRegionPercent":"0.42","urlId":"investicionno-stroitelnaja-kompanija-real-stroj-6024088001"},{"apartmentsCountAll":5,"apartmentsCountSales":5,"buildingVolume":"1133","coefficientRating":"1.55","complexesCountAll":2,"complexesCountSales":1,"filteredApartmentsCount":5,"filteredComplexCount":1,"filteredGkCount":0,"filteredOrgCount":1,"filteredPtCount":0,"foundationYear":"2008","gkCountSales":1,"id":"5207072001","maxApartmentCostM2":"51316","maxCostMillion":"2.9","minApartmentCostM2":"47778","minCostMillion":"1.95","name":"СХ Флагман","orgCountAll":2,"orgCountSales":1,"ptCountSales":0,"rating":"1.5","region":"Хабаровский край","regionKey":"145501001","regionPlace":"42","rfPlace":"3172","shareRegionPercent":"0.22","urlId":"stroitelnyj-kholding-flagman-5207072001"},{"apartmentsCountAll":1,"apartmentsCountSales":1,"complexesCountAll":1,"complexesCountSales":1,"filteredApartmentsCount":1,"filteredComplexCount":1,"filteredGkCount":0,"filteredOrgCount":1,"filteredPtCount":0,"foundationYear":"2014","gkCountSales":1,"id":"7690639001","maxApartmentCostM2":"92784","maxCostMillion":"1.8","minApartmentCostM2":"92784","minCostMillion":"1.8","name":"Бизнес-Центр 3","orgCountAll":1,"orgCountSales":1,"ptCountSales":0,"region":"Хабаровский край","regionKey":"145501001","urlId":"biznes-centr-3-7690639001"}]