{"address":"Красноярский край, г.Красноярск, ул. Телевизорная, д.4Б","apartmentsCount":"125","building":{"monthDelay":"11.67","nallsquare":"107779","postponeM2":"57996.0","postponePercent":"53.81"},"courseOfConstruction":{"build":{"allApartments":"125","gk":"4","pt":"0"},"finish":{"allApartments":"0","gk":"0","pt":"0"},"stageApartmentCount":"125","stop":{"allApartments":"0","gk":"0","pt":"0"}},"developers_count":"3","endToInvestors":"false","ratingErz":["1.00","1.00"],"full_name":"Группа компаний Зодчий","gk_count":"6","htmlPage":{"description":"Группа компаний Зодчий - цены на квартиры в новостройках, описание компании, контакты.","index":"index_follow","title":"Группа компаний Зодчий - информация о бренде, новостройки на карте, рейтинг - ЕРЗ.","url":"gruppa-kompanij-zodchij-4350167001"},"id":"4350167001","input2016":{"monthDelay":"10.8","nallsquare":"9729","postponeM2":"9729.0","postponePercent":"100.0"},"input2017":{"monthDelay":"8.9","nallsquare":"3502","postponeM2":"3502.0","postponePercent":"100.0"},"isHiddenConsumer":"1","logotype":"erz-rest/api/v1/document?id=4350244001&type=LOGO&nocache=1562425739864","management":{"management":{"surname":"Шабунин","name":"Владимир","secondname":"Дмитриевич","position":"генеральный директор"}},"maxDedit":"2019-04-11","name":"ГК Зодчий","newsCount":"1","ntype":"0","pt_count":"0","rating_rask":"В1","regionsDate":"01.07.2019","regions_count":"1","salesDepartmentPhone":"(391) 2560353","salesRegion":{"salesRegion":{"apartmentsCount":"125","averagePrice":"42231","gkCount":"4","isHiddenConsumer":"1","ptCount":"0","regionKey":"143082001","regionName":"Красноярский край"}},"salesRegionCount":"1","site":"zodchiysk.ru","place":"244","urlId":"gruppa-kompanij-zodchij-4350167001","viewCount":"513","volume_of_building":"107779","year_of_foundation":"1997"}