{"address":"Калужская область, г.Калуга, ул. Труда, д.15","apartmentsCount":"30","building":{"monthDelay":"0.0","nallsquare":"3050","postponeM2":"0.0","postponePercent":"0.0"},"courseOfConstruction":{"build":{"allApartments":"30","gk":"1","pt":"0"},"finish":{"allApartments":"0","gk":"0","pt":"0"},"stageApartmentCount":"30","stop":{"allApartments":"0","gk":"0","pt":"0"}},"developers_count":"2","endToInvestors":"false","full_name":"Группа компаний Росинстрой-Нордис","gk_count":"1","htmlPage":{"description":"Группа компаний Росинстрой-Нордис - цены на квартиры в новостройках, описание компании, контакты.","index":"index_follow","title":"Группа компаний Росинстрой-Нордис - информация о бренде, новостройки на карте, рейтинг - ЕРЗ.","url":"gruppa-kompanij-rosinstroj-nordis-4207570001"},"id":"4207570001","input2016":{"monthDelay":"0.59","nallsquare":"9782","postponeM2":"3609.0","postponePercent":"36.89"},"isHiddenConsumer":"0","logotype":"erz-rest/api/v1/document?id=4208218001&type=LOGO&nocache=1562425593530","management":{"management":{"surname":"Антонов","name":"Сергей","secondname":"Анатольевич","position":"директор"}},"maxDedit":"2018-09-20","name":"ГК Росинстрой-Нордис","newsCount":"0","ntype":"0","pt_count":"0","rating_rask":"В2","regionsDate":"01.07.2019","regions_count":"1","salesDepartmentPhone":"(4842) 228298, (910) 7071788","salesRegion":{"salesRegion":{"apartmentsCount":"30","averagePrice":"45369","gkCount":"1","isHiddenConsumer":"0","ptCount":"0","regionKey":"142678001","regionName":"Калужская область"}},"salesRegionCount":"1","site":"rosinstroy.org","place":"2817","urlId":"gruppa-kompanij-rosinstroj-nordis-4207570001","viewCount":"67","volume_of_building":"3050","year_of_foundation":"2005"}