{"address":"Московская область, г.Подольск, ул. Вишневая, д.11 А, корп.2","apartmentsCount":"217","building":{"monthDelay":"33.0","nallsquare":"28076","postponeM2":"28076.0","postponePercent":"100.0"},"courseOfConstruction":{"build":{"allApartments":"6","gk":"1","pt":"0"},"finish":{"allApartments":"211","gk":"1","pt":"0"},"stageApartmentCount":"217","stop":{"allApartments":"0","gk":"0","pt":"0"}},"developers_count":"1","endToInvestors":"false","ratingErz":["1.50","1.50"],"facebook":"https://www.facebook.com/sochi123official","full_name":"Компания Универсал","gk_count":"1","htmlPage":{"description":"Компания Универсал - цены на квартиры в новостройках, описание компании, контакты.","index":"index_follow","title":"Компания Универсал - информация о бренде, новостройки на карте, рейтинг - ЕРЗ.","url":"kompanija-universal-5567737001"},"id":"5567737001","input2018":{"monthDelay":"7.86","nallsquare":"58397","postponeM2":"58397.0","postponePercent":"100.0"},"isHiddenConsumer":"0","management":{"management":{"surname":"Кандауров","name":"Дмитрий","secondname":"Сергеевич","position":"директор"}},"maxDedit":"2018-08-27","mentioning":{"mentioning":{"title":"Первый корпус ЖК «Раз. Два. Три» введен в эксплуатацию","annotation":"В Сочи стало на 350 обманутых дольщиков меньше: накануне в администрации Сочи был подписан документ о введении в эксплуатацию корпуса В ЖК «Раз. Два. Три», находящегося в Центральном районе курорта. Застройщик ООО «Универсал» также подал в администрацию заявку на введение в эксплуатацию корпуса под литерой Б, ответ на которую будет дан в течение двух недель, сообщает пресс-служба мэрии.","rating":"положительная","source":"Интернет-портал СочиИнформБюро","date":"22 августа 2018","vlink":"https://sochi-informburo.ru/2018/08/22/30824-pervyj-korpus-zhk-raz-dva-tri-vveden-v-jekspluataciju/"}},"name":"Компания Универсал","newsCount":"0","ntype":"0","ok":"https://ok.ru/group/58247646085164","pt_count":"0","rating_rask":"В2","regionsDate":"01.07.2019","regions_count":"1","salesDepartmentPhone":"(862) 2913123, (862) 2914123","salesRegion":{"salesRegion":{"apartmentsCount":"217","averagePrice":"124533","gkCount":"1","isHiddenConsumer":"0","ptCount":"0","regionKey":"143001001","regionName":"Краснодарский край"}},"salesRegionCount":"1","site":"sochi123a.com/","place":"865","urlId":"kompanija-universal-5567737001","viewCount":"638","vk":"https://vk.com/sochi123_official","volume_of_building":"28076","year_of_foundation":"2012"}