{"address":"г.Санкт-Петербург, ул. Миллионная, д.8","apartmentsCount":"189","building":{"monthDelay":"7.02","nallsquare":"119793","postponeM2":"26213.0","postponePercent":"21.88"},"courseOfConstruction":{"build":{"allApartments":"188","gk":"4","pt":"0"},"finish":{"allApartments":"1","gk":"1","pt":"0"},"stageApartmentCount":"189","stop":{"allApartments":"0","gk":"0","pt":"0"}},"developers_count":"6","endToInvestors":"false","ratingErz":["1.00","1.00"],"full_name":"Производственное объединение Ленстройматериалы","gk_count":"5","htmlPage":{"description":"Производственное объединение Ленстройматериалы - цены на квартиры в новостройках, описание компании, контакты.","index":"index_follow","title":"Производственное объединение Ленстройматериалы - информация о бренде, новостройки на карте, рейтинг - ЕРЗ.","url":"proizvodstvennoe-obedinenie-lenstrojmaterialy-1606111001"},"id":"1606111001","input2016":{"monthDelay":"2.38","nallsquare":"30472","postponeM2":"14824.0","postponePercent":"48.65"},"input2017":{"monthDelay":"13.49","nallsquare":"67576","postponeM2":"67576.0","postponePercent":"100.0"},"input2018":{"monthDelay":"11.13","nallsquare":"21415","postponeM2":"21415.0","postponePercent":"100.0"},"isHiddenConsumer":"0","logotype":"erz-rest/api/v1/document?id=3755738001&type=LOGO&nocache=1562425600368","management":{"management":{"surname":"Игнатьев","name":"Дмитрий","secondname":"Иванович","position":"генеральный директор"}},"maxDedit":"2018-09-14","mentioning":{"mentioning":{"title":"Компания «ЛСТ Гатчина» вводит в эксплуатацию первую очередь жилого квартала «IQ Гатчина» в Ленобласти","annotation":"Компания «ЛСТ Гатчина» (Группа «Ленстройматериалы») получила разрешение на ввод в эксплуатацию первой очереди жилого комплекса эконом-класса «IQ Гатчина» на Пушкинском шоссе, 13, корпус 1, 2, 3, 4, 5, 6 ,блок 1,2,3 в городе Гатчина Ленинградской области.","rating":"положительная","source":"Restate.ru","date":"23 апреля 2017","vlink":"https://www.restate.ru/material/kompaniya-lst-gatchina-vvodit-v-ekspluataciyu-pervuyu-ochered-zhilogo-kvartala-iq-gatchina-v-164844.html"}},"name":"ПО Ленстройматериалы","newsCount":"0","ntype":"0","pt_count":"0","rating_rask":"Б2","regionsDate":"01.07.2019","regions_count":"2","salesDepartmentPhone":"(812) 6543210","salesRegion":{"salesRegion":[{"apartmentsCount":"173","averagePrice":"73241","gkCount":"3","isHiddenConsumer":"0","ptCount":"0","regionKey":"143275001","regionName":"Ленинградская область"},{"apartmentsCount":"16","averagePrice":"84246","gkCount":"1","isHiddenConsumer":"0","ptCount":"0","regionKey":"144781001","regionName":"г.Санкт-Петербург"}]},"salesRegionCount":"2","site":"78stroy.ru","place":"214","urlId":"proizvodstvennoe-obedinenie-lenstrojmaterialy-1606111001","viewCount":"991","volume_of_building":"119793","year_of_foundation":"1992"}