{"address":"г.Москва, ш. Волоколамское, д.69","apartmentsCount":"191","building":{"monthDelay":"1.84","nallsquare":"267457","postponeM2":"81965.0","postponePercent":"30.65"},"courseOfConstruction":{"build":{"allApartments":"191","gk":"1","pt":"0"},"finish":{"allApartments":"0","gk":"0","pt":"0"},"stageApartmentCount":"191","stop":{"allApartments":"0","gk":"0","pt":"0"}},"developers_count":"1","endToInvestors":"false","ratingErz":["4.00","4.00"],"full_name":"Стадион Спартак","gk_count":"2","htmlPage":{"description":"Стадион Спартак - цены на квартиры в новостройках, описание компании, контакты.","index":"index_follow","title":"Стадион Спартак - информация о бренде, новостройки на карте, рейтинг - ЕРЗ.","url":"stadion-spartak-10336172001"},"id":"10336172001","input2017":{"monthDelay":"0.0","nallsquare":"46196","postponeM2":"0.0","postponePercent":"0.0"},"input2019":{"monthDelay":"4.4","nallsquare":"64188","postponeM2":"64188.0","postponePercent":"100.0"},"isHiddenConsumer":"0","management":{"management":{"surname":"Федун","name":"Андрей","secondname":"Арнольдович","position":"генеральный директор"}},"maxDedit":"2019-06-19","name":"Стадион Спартак","newsCount":"0","ntype":"0","pt_count":"0","regionsDate":"01.07.2019","regions_count":"1","salesDepartmentPhone":"(495) 1232018","salesRegion":{"salesRegion":{"apartmentsCount":"191","averagePrice":"178928","gkCount":"1","isHiddenConsumer":"0","ptCount":"0","regionKey":"143443001","regionName":"г.Москва"}},"salesRegionCount":"1","site":"tushino2018.ru/","place":"74","urlId":"stadion-spartak-10336172001","viewCount":"257","volume_of_building":"267457","year_of_foundation":"2004"}