[{"apartmentsCountAll":"1316","apartmentsCountSales":"797","buildingVolume":"88319","coefficientRating":"100","complexesCountAll":"4","complexesCountSales":"3","filteredApartmentsCount":"797","filteredComplexCount":"3","filteredGkCount":"0","filteredOrgCount":"1","filteredPtCount":"0","foundationYear":"1999","gkCountSales":"3","id":"2992531001","maxApartmentCostM2":"80000","maxCostMillion":"7.45","minApartmentCostM2":"34500","minCostMillion":"1.16","name":"Инстеп","orgCountAll":"1","orgCountSales":"1","ptCountSales":"0","rating":"4","region":"Курская область","regionKey":"143245001","regionPlace":"1","rfPlace":"186","shareRegionPercent":"20.81","urlId":"instep-2992531001"},{"apartmentsCountAll":"11","apartmentsCountSales":"4","buildingVolume":"81696","coefficientRating":"94.31","complexesCountAll":"4","complexesCountSales":"3","filteredApartmentsCount":"4","filteredComplexCount":"3","filteredGkCount":"0","filteredOrgCount":"1","filteredPtCount":"0","foundationYear":"2007","gkCountSales":"3","id":"5873338001","maxApartmentCostM2":"40000","maxCostMillion":"2.39","minApartmentCostM2":"32983","minCostMillion":"1.32","name":"ГлавСтрой","orgCountAll":"1","orgCountSales":"1","ptCountSales":"0","rating":"3","region":"Курская область","regionKey":"143245001","regionPlace":"2","rfPlace":"319","shareRegionPercent":"19.32","urlId":"glavstroj-5873338001"},{"apartmentsCountAll":"1","apartmentsCountSales":"1","buildingVolume":"40801","coefficientRating":"47.1","complexesCountAll":"1","complexesCountSales":"1","filteredApartmentsCount":"1","filteredComplexCount":"1","filteredGkCount":"0","filteredOrgCount":"1","filteredPtCount":"0","foundationYear":"2016","gkCountSales":"1","id":"10108851001","maxApartmentCostM2":"43253","maxCostMillion":"1.25","minApartmentCostM2":"43253","minCostMillion":"1.25","name":"ТЕХЗАКАЗСТРОЙ","orgCountAll":"1","orgCountSales":"1","ptCountSales":"0","region":"Курская область","regionKey":"143245001","regionPlace":"3","rfPlace":"648","shareRegionPercent":"9.65","urlId":"-tekhzakazstroj-10108851001"},{"apartmentsCountAll":"4","apartmentsCountSales":"3","buildingVolume":"36805","coefficientRating":"42.49","complexesCountAll":"6","complexesCountSales":"2","filteredApartmentsCount":"3","filteredComplexCount":"2","filteredGkCount":"0","filteredOrgCount":"1","filteredPtCount":"0","foundationYear":"1965","gkCountSales":"2","id":"1394731001","maxApartmentCostM2":"32500","maxCostMillion":"1.92","minApartmentCostM2":"30000","minCostMillion":"0.99","name":"ГК Железногорская МСО","orgCountAll":"2","orgCountSales":"1","ptCountSales":"0","rating":"1.5","region":"Курская область","regionKey":"143245001","regionPlace":"4","rfPlace":"373","shareRegionPercent":"8.7","urlId":"gruppa-kompanij-zheleznogorskaja-mso-1394731001"},{"apartmentsCountAll":"4","apartmentsCountSales":"4","buildingVolume":"29503","coefficientRating":"34.06","complexesCountAll":"2","complexesCountSales":"2","filteredApartmentsCount":"4","filteredComplexCount":"2","filteredGkCount":"0","filteredOrgCount":"1","filteredPtCount":"0","foundationYear":"1958","gkCountSales":"2","id":"5834050001","maxApartmentCostM2":"32125","maxCostMillion":"1.39","minApartmentCostM2":"29344","minCostMillion":"0.83","name":"ГК ЗЖБИ-3","orgCountAll":"1","orgCountSales":"1","ptCountSales":"0","rating":"2.5","region":"Курская область","regionKey":"143245001","regionPlace":"5","rfPlace":"843","shareRegionPercent":"6.98","urlId":"gruppa-predprijatij-zavod-zhbi-3-5834050001"},{"apartmentsCountAll":"3","apartmentsCountSales":"3","buildingVolume":"18148","coefficientRating":"20.95","complexesCountAll":"1","complexesCountSales":"1","filteredApartmentsCount":"3","filteredComplexCount":"1","filteredGkCount":"0","filteredOrgCount":"1","filteredPtCount":"0","foundationYear":"1993","gkCountSales":"1","id":"5885708001","maxApartmentCostM2":"43000","maxCostMillion":"1.77","minApartmentCostM2":"39000","minCostMillion":"1.62","name":"ИНЖЕНЕР","orgCountAll":"1","orgCountSales":"1","ptCountSales":"0","rating":"5","region":"Курская область","regionKey":"143245001","regionPlace":"6","rfPlace":"1222","shareRegionPercent":"4.29","urlId":"inzhener-5885708001"},{"apartmentsCountAll":"1","apartmentsCountSales":"1","buildingVolume":"13729","coefficientRating":"15.85","complexesCountAll":"1","complexesCountSales":"1","filteredApartmentsCount":"1","filteredComplexCount":"1","filteredGkCount":"0","filteredOrgCount":"1","filteredPtCount":"0","foundationYear":"2002","gkCountSales":"1","id":"5881743001","maxApartmentCostM2":"42000","maxCostMillion":"1.82","minApartmentCostM2":"42000","minCostMillion":"1.82","name":"Фирма Перспектива плюс","orgCountAll":"1","orgCountSales":"1","ptCountSales":"0","region":"Курская область","regionKey":"143245001","regionPlace":"8","rfPlace":"1460","shareRegionPercent":"3.25","urlId":"firma-perspektiva-pljus-5881743001"},{"apartmentsCountAll":"2","apartmentsCountSales":"2","buildingVolume":"12557","coefficientRating":"14.5","complexesCountAll":"2","complexesCountSales":"1","filteredApartmentsCount":"2","filteredComplexCount":"1","filteredGkCount":"0","filteredOrgCount":"1","filteredPtCount":"0","foundationYear":"1971","gkCountSales":"1","id":"6004581001","maxApartmentCostM2":"28000","maxCostMillion":"1.34","minApartmentCostM2":"27816","minCostMillion":"1.33","name":"Центрметаллургмонтаж","orgCountAll":"1","orgCountSales":"1","ptCountSales":"0","rating":"3","region":"Курская область","regionKey":"143245001","regionPlace":"9","rfPlace":"1557","shareRegionPercent":"2.97","urlId":"centrmetallurgmontazh-6004581001"},{"apartmentsCountAll":"5","apartmentsCountSales":"1","buildingVolume":"11852","coefficientRating":"13.68","complexesCountAll":"3","complexesCountSales":"1","filteredApartmentsCount":"1","filteredComplexCount":"1","filteredGkCount":"0","filteredOrgCount":"1","filteredPtCount":"0","foundationYear":"2006","gkCountSales":"1","id":"5880668001","maxApartmentCostM2":"38000","maxCostMillion":"1.65","minApartmentCostM2":"38000","minCostMillion":"1.65","name":"СК Эльдекор XXI плюс","orgCountAll":"1","orgCountSales":"1","ptCountSales":"0","rating":"5","region":"Курская область","regionKey":"143245001","regionPlace":"10","rfPlace":"1612","shareRegionPercent":"2.8","urlId":"stroitelnaja-kompanija-eldekor-xxi-pljus-5880668001"},{"apartmentsCountAll":"2","apartmentsCountSales":"2","buildingVolume":"5999","coefficientRating":"6.93","complexesCountAll":"1","complexesCountSales":"1","filteredApartmentsCount":"2","filteredComplexCount":"1","filteredGkCount":"0","filteredOrgCount":"1","filteredPtCount":"0","foundationYear":"2010","gkCountSales":"1","id":"7740395001","maxApartmentCostM2":"33000","maxCostMillion":"2.08","minApartmentCostM2":"33000","minCostMillion":"1.55","name":"ГК КССМ","orgCountAll":"1","orgCountSales":"1","ptCountSales":"0","region":"Курская область","regionKey":"143245001","regionPlace":"14","rfPlace":"2331","shareRegionPercent":"1.42","urlId":"-gruppa-kompanij-kurskspecstrojmekhanizacija-7740395001"},{"apartmentsCountAll":"3","apartmentsCountSales":"1","buildingVolume":"4926","coefficientRating":"5.69","complexesCountAll":"3","complexesCountSales":"1","filteredApartmentsCount":"1","filteredComplexCount":"1","filteredGkCount":"0","filteredOrgCount":"1","filteredPtCount":"0","foundationYear":"2004","gkCountSales":"1","id":"1271319001","maxApartmentCostM2":"37666","maxCostMillion":"1.42","minApartmentCostM2":"37666","minCostMillion":"1.42","name":"ГК СКБ Групп","orgCountAll":"3","orgCountSales":"1","ptCountSales":"0","rating":"1.5","region":"Курская область","regionKey":"143245001","regionPlace":"15","rfPlace":"2517","shareRegionPercent":"1.16","urlId":"gruppa-kompanij-skb-grupp-1271319001"},{"apartmentsCountAll":"6","apartmentsCountSales":"6","buildingVolume":"4847","coefficientRating":"5.6","complexesCountAll":"2","complexesCountSales":"1","filteredApartmentsCount":"6","filteredComplexCount":"1","filteredGkCount":"0","filteredOrgCount":"1","filteredPtCount":"0","foundationYear":"1991","gkCountSales":"0","id":"7409580001","maxApartmentCostM2":"30144","maxCostMillion":"6.3","minApartmentCostM2":"30144","minCostMillion":"6.3","name":"КонЪ","orgCountAll":"1","orgCountSales":"1","ptCountSales":"1","region":"Курская область","regionKey":"143245001","regionPlace":"16","rfPlace":"2526","shareRegionPercent":"1.15","urlId":"-stroitelno-montazhnaja-firma-kon-7409580001"},{"apartmentsCountAll":"1","apartmentsCountSales":"1","buildingVolume":"4176","coefficientRating":"4.82","complexesCountAll":"2","complexesCountSales":"1","filteredApartmentsCount":"1","filteredComplexCount":"1","filteredGkCount":"0","filteredOrgCount":"1","filteredPtCount":"0","foundationYear":"2002","gkCountSales":"1","id":"7736462001","maxApartmentCostM2":"37736","maxCostMillion":"2.0","minApartmentCostM2":"37736","minCostMillion":"2.0","name":"КОИА","orgCountAll":"1","orgCountSales":"1","ptCountSales":"0","region":"Курская область","regionKey":"143245001","regionPlace":"19","rfPlace":"2634","shareRegionPercent":"0.99","urlId":"-kurskoe-oblastnoe-ipotechnoe-agentstvo-7736462001"},{"apartmentsCountAll":"3","apartmentsCountSales":"3","buildingVolume":"3896","coefficientRating":"4.5","complexesCountAll":"4","complexesCountSales":"1","filteredApartmentsCount":"3","filteredComplexCount":"1","filteredGkCount":"0","filteredOrgCount":"1","filteredPtCount":"0","foundationYear":"2002","gkCountSales":"1","id":"6003461001","maxApartmentCostM2":"45999","maxCostMillion":"2.42","minApartmentCostM2":"44992","minCostMillion":"1.85","name":"ТСК Веста","orgCountAll":"1","orgCountSales":"1","ptCountSales":"0","rating":"5","region":"Курская область","regionKey":"143245001","regionPlace":"20","rfPlace":"2675","shareRegionPercent":"0.92","urlId":"torgovo-stroitelnaja-kompanija-vesta-6003461001"},{"apartmentsCountAll":"3","apartmentsCountSales":"3","complexesCountAll":"1","complexesCountSales":"1","filteredApartmentsCount":"3","filteredComplexCount":"1","filteredGkCount":"0","filteredOrgCount":"1","filteredPtCount":"0","foundationYear":"2011","gkCountSales":"1","id":"6050132001","maxApartmentCostM2":"36000","maxCostMillion":"2.64","minApartmentCostM2":"36000","minCostMillion":"1.47","name":"СМУ № 2","orgCountAll":"1","orgCountSales":"1","ptCountSales":"0","region":"Курская область","regionKey":"143245001","urlId":"stroitelno-montazhnoe-upravlenie-№-2-6050132001"},{"apartmentsCountAll":"1","apartmentsCountSales":"1","complexesCountAll":"1","complexesCountSales":"1","filteredApartmentsCount":"1","filteredComplexCount":"1","filteredGkCount":"0","filteredOrgCount":"1","filteredPtCount":"0","foundationYear":"2014","gkCountSales":"1","id":"6049208001","maxApartmentCostM2":"47458","maxCostMillion":"2.8","minApartmentCostM2":"47458","minCostMillion":"2.8","name":"Росинка","orgCountAll":"1","orgCountSales":"1","ptCountSales":"0","region":"Курская область","regionKey":"143245001","urlId":"rosinka-6049208001"}]