[{"apartmentsCountAll":"966","apartmentsCountSales":"673","buildingVolume":"293579","coefficientRating":"100","complexesCountAll":"10","complexesCountSales":"5","filteredApartmentsCount":"673","filteredComplexCount":"5","filteredGkCount":"0","filteredOrgCount":"7","filteredPtCount":"0","foundationYear":"1997","gkCountSales":"5","id":"452311001","maxApartmentCostM2":"43187","maxCostMillion":"3.73","minApartmentCostM2":"32500","minCostMillion":"0.97","name":"ГК Гарант БКЖС","orgCountAll":"13","orgCountSales":"7","ptCountSales":"0","rating":"2","region":"Брянская область","regionKey":"144235001","regionPlace":"1","rfPlace":"64","shareRegionPercent":"23.11","urlId":"gruppa-kompanij-garant-bkzhs-452311001"},{"apartmentsCountAll":"1266","apartmentsCountSales":"579","buildingVolume":"104787","coefficientRating":"35.69","complexesCountAll":"11","complexesCountSales":"6","filteredApartmentsCount":"579","filteredComplexCount":"6","filteredGkCount":"0","filteredOrgCount":"2","filteredPtCount":"0","foundationYear":"1992","gkCountSales":"6","id":"2948765001","maxApartmentCostM2":"41500","maxCostMillion":"4.71","minApartmentCostM2":"31000","minCostMillion":"0.93","name":"ГК Надежда","orgCountAll":"3","orgCountSales":"2","ptCountSales":"0","rating":"4","region":"Брянская область","regionKey":"144235001","regionPlace":"2","rfPlace":"252","shareRegionPercent":"8.25","urlId":"gruppa-kompanij-nadezhda-2948765001"},{"apartmentsCountAll":"624","apartmentsCountSales":"372","buildingVolume":"91787","coefficientRating":"31.26","complexesCountAll":"2","complexesCountSales":"1","filteredApartmentsCount":"372","filteredComplexCount":"1","filteredGkCount":"0","filteredOrgCount":"1","filteredPtCount":"0","foundationYear":"2005","gkCountSales":"1","id":"5834562001","maxApartmentCostM2":"38000","maxCostMillion":"3.15","minApartmentCostM2":"28000","minCostMillion":"1.06","name":"ПРЕМИУМ ПРОЕКТ","orgCountAll":"1","orgCountSales":"1","ptCountSales":"0","rating":"2","region":"Брянская область","regionKey":"144235001","regionPlace":"3","rfPlace":"293","shareRegionPercent":"7.22","urlId":"premium-proekt-5834562001"},{"apartmentsCountAll":"664","apartmentsCountSales":"352","buildingVolume":"80059","coefficientRating":"27.27","complexesCountAll":"5","complexesCountSales":"3","filteredApartmentsCount":"352","filteredComplexCount":"3","filteredGkCount":"0","filteredOrgCount":"1","filteredPtCount":"0","foundationYear":"2002","gkCountSales":"3","id":"5867368001","maxApartmentCostM2":"36000","maxCostMillion":"3.15","minApartmentCostM2":"27000","minCostMillion":"0.99","name":"БСК","orgCountAll":"1","orgCountSales":"1","ptCountSales":"0","rating":"3.5","region":"Брянская область","regionKey":"144235001","regionPlace":"4","rfPlace":"340","shareRegionPercent":"6.3","urlId":"brjanskaja-stroitelnaja-kompanija-5867368001"},{"apartmentsCountAll":"16","apartmentsCountSales":"14","buildingVolume":"73875","coefficientRating":"25.16","complexesCountAll":"11","complexesCountSales":"6","filteredApartmentsCount":"14","filteredComplexCount":"6","filteredGkCount":"0","filteredOrgCount":"1","filteredPtCount":"0","foundationYear":"2003","gkCountSales":"6","id":"6007835001","maxApartmentCostM2":"48260","maxCostMillion":"3.71","minApartmentCostM2":"35700","minCostMillion":"1.33","name":"Застройщик АТМОСФЕРА","orgCountAll":"1","orgCountSales":"1","ptCountSales":"0","rating":"3.5","region":"Брянская область","regionKey":"144235001","regionPlace":"5","rfPlace":"370","shareRegionPercent":"5.81","urlId":"zastroyshchik-ATMOSFERA-6007835001"},{"apartmentsCountAll":"11","apartmentsCountSales":"8","buildingVolume":"67877","coefficientRating":"23.12","complexesCountAll":"5","complexesCountSales":"2","filteredApartmentsCount":"8","filteredComplexCount":"2","filteredGkCount":"0","filteredOrgCount":"1","filteredPtCount":"0","foundationYear":"2010","gkCountSales":"2","id":"3104931001","maxApartmentCostM2":"36200","maxCostMillion":"3.46","minApartmentCostM2":"35100","minCostMillion":"1.51","name":"СЗ Мегаполис-Строй","orgCountAll":"1","orgCountSales":"1","ptCountSales":"0","rating":"5","region":"Брянская область","regionKey":"144235001","regionPlace":"6","rfPlace":"407","shareRegionPercent":"5.34","urlId":"specializirovannyj-zastrojshchik-megapolis-stroj-3104931001"},{"apartmentsCountAll":"361","apartmentsCountSales":"133","buildingVolume":"52644","coefficientRating":"17.93","complexesCountAll":"4","complexesCountSales":"3","filteredApartmentsCount":"133","filteredComplexCount":"3","filteredGkCount":"0","filteredOrgCount":"2","filteredPtCount":"0","foundationYear":"2005","gkCountSales":"3","id":"5874179001","maxApartmentCostM2":"38000","maxCostMillion":"8.16","minApartmentCostM2":"28000","minCostMillion":"1.25","name":"ГК СтройГарант","orgCountAll":"3","orgCountSales":"2","ptCountSales":"0","rating":"2","region":"Брянская область","regionKey":"144235001","regionPlace":"7","rfPlace":"524","shareRegionPercent":"4.14","urlId":"gruppa-kompanij-strojgarant-5874179001"},{"apartmentsCountAll":"463","apartmentsCountSales":"190","buildingVolume":"48411","coefficientRating":"16.49","complexesCountAll":"3","complexesCountSales":"1","filteredApartmentsCount":"190","filteredComplexCount":"1","filteredGkCount":"0","filteredOrgCount":"1","filteredPtCount":"0","foundationYear":"1991","gkCountSales":"1","id":"5903524001","maxApartmentCostM2":"37000","maxCostMillion":"5.09","minApartmentCostM2":"36000","minCostMillion":"1.64","name":"Форвард","orgCountAll":"1","orgCountSales":"1","ptCountSales":"0","rating":"5","region":"Брянская область","regionKey":"144235001","regionPlace":"8","rfPlace":"571","shareRegionPercent":"3.81","urlId":"forvard-5903524001"},{"apartmentsCountAll":"24","apartmentsCountSales":"18","buildingVolume":"44207","coefficientRating":"15.06","complexesCountAll":"10","complexesCountSales":"6","filteredApartmentsCount":"18","filteredComplexCount":"6","filteredGkCount":"0","filteredOrgCount":"1","filteredPtCount":"0","foundationYear":"2000","gkCountSales":"6","id":"5873644001","maxApartmentCostM2":"34000","maxCostMillion":"3.23","minApartmentCostM2":"30000","minCostMillion":"1.08","name":"ГК Инстрой","orgCountAll":"1","orgCountSales":"1","ptCountSales":"0","rating":"4.5","region":"Брянская область","regionKey":"144235001","regionPlace":"9","rfPlace":"612","shareRegionPercent":"3.48","urlId":"kompanija-instroj-5873644001"},{"apartmentsCountAll":"663","apartmentsCountSales":"438","buildingVolume":"28254","coefficientRating":"9.62","complexesCountAll":"7","complexesCountSales":"7","filteredApartmentsCount":"438","filteredComplexCount":"7","filteredGkCount":"0","filteredOrgCount":"2","filteredPtCount":"0","foundationYear":"2001","gkCountSales":"7","id":"536237001","maxApartmentCostM2":"41536","maxCostMillion":"3.5","minApartmentCostM2":"31715","minCostMillion":"1.42","name":"САКС","orgCountAll":"2","orgCountSales":"2","ptCountSales":"0","rating":"5","region":"Брянская область","regionKey":"144235001","regionPlace":"11","rfPlace":"860","shareRegionPercent":"2.22","urlId":"saks-536237001"},{"apartmentsCountAll":"1","apartmentsCountSales":"1","buildingVolume":"24156","coefficientRating":"8.23","complexesCountAll":"3","complexesCountSales":"1","filteredApartmentsCount":"1","filteredComplexCount":"1","filteredGkCount":"0","filteredOrgCount":"1","filteredPtCount":"0","foundationYear":"1992","gkCountSales":"1","id":"6023700001","maxApartmentCostM2":"32500","maxCostMillion":"1.07","minApartmentCostM2":"32500","minCostMillion":"1.07","name":"СКФ Комфорт","orgCountAll":"1","orgCountSales":"1","ptCountSales":"0","rating":"3.5","region":"Брянская область","regionKey":"144235001","regionPlace":"11","rfPlace":"977","shareRegionPercent":"1.89","urlId":"stroitelno-kommercheskaja-firma-komfort-6023700001"},{"apartmentsCountAll":"71","apartmentsCountSales":"23","buildingVolume":"20903","coefficientRating":"7.12","complexesCountAll":"1","complexesCountSales":"1","filteredApartmentsCount":"23","filteredComplexCount":"1","filteredGkCount":"0","filteredOrgCount":"1","filteredPtCount":"0","foundationYear":"2012","gkCountSales":"1","id":"6554921001","maxApartmentCostM2":"62000","maxCostMillion":"9.41","minApartmentCostM2":"53000","minCostMillion":"3.08","name":"Касабланка","orgCountAll":"1","orgCountSales":"1","ptCountSales":"0","region":"Брянская область","regionKey":"144235001","regionPlace":"13","rfPlace":"1083","shareRegionPercent":"1.64","urlId":"kasablanka-6554921001"},{"apartmentsCountAll":"6","apartmentsCountSales":"2","buildingVolume":"16054","coefficientRating":"5.47","complexesCountAll":"1","complexesCountSales":"1","filteredApartmentsCount":"2","filteredComplexCount":"1","filteredGkCount":"0","filteredOrgCount":"1","filteredPtCount":"0","foundationYear":"2017","gkCountSales":"1","id":"6531578001","maxApartmentCostM2":"33000","maxCostMillion":"1.6","minApartmentCostM2":"31000","minCostMillion":"1.51","name":"Никаинвестстрой","orgCountAll":"1","orgCountSales":"1","ptCountSales":"0","region":"Брянская область","regionKey":"144235001","regionPlace":"14","rfPlace":"1321","shareRegionPercent":"1.26","urlId":"nikainveststroj-6531578001"},{"apartmentsCountAll":"9","apartmentsCountSales":"2","buildingVolume":"15165","coefficientRating":"5.17","complexesCountAll":"5","complexesCountSales":"2","filteredApartmentsCount":"2","filteredComplexCount":"2","filteredGkCount":"0","filteredOrgCount":"1","filteredPtCount":"0","foundationYear":"1992","gkCountSales":"2","id":"5881214001","maxApartmentCostM2":"31421","maxCostMillion":"1.38","minApartmentCostM2":"28000","minCostMillion":"1.37","name":"Домострой","orgCountAll":"1","orgCountSales":"1","ptCountSales":"0","rating":"5","region":"Брянская область","regionKey":"144235001","regionPlace":"15","rfPlace":"1377","shareRegionPercent":"1.19","urlId":"stroitelnaja-kompanija-domostroj-5881214001"},{"apartmentsCountAll":"290","apartmentsCountSales":"153","buildingVolume":"14086","coefficientRating":"4.8","complexesCountAll":"5","complexesCountSales":"2","filteredApartmentsCount":"153","filteredComplexCount":"2","filteredGkCount":"0","filteredOrgCount":"1","filteredPtCount":"0","foundationYear":"2012","gkCountSales":"2","id":"536152001","maxApartmentCostM2":"34000","maxCostMillion":"3.11","minApartmentCostM2":"33000","minCostMillion":"1.29","name":"БизнесСфера","orgCountAll":"2","orgCountSales":"1","ptCountSales":"0","rating":"4.5","region":"Брянская область","regionKey":"144235001","regionPlace":"16","rfPlace":"1446","shareRegionPercent":"1.11","urlId":"biznessfera-536152001"},{"apartmentsCountAll":"2","apartmentsCountSales":"2","buildingVolume":"12932","coefficientRating":"4.4","complexesCountAll":"2","complexesCountSales":"1","filteredApartmentsCount":"2","filteredComplexCount":"1","filteredGkCount":"0","filteredOrgCount":"1","filteredPtCount":"0","foundationYear":"2004","gkCountSales":"1","id":"6031273001","maxApartmentCostM2":"35000","maxCostMillion":"1.68","minApartmentCostM2":"35000","minCostMillion":"1.54","name":"СМУ Строитель-Сервис","orgCountAll":"1","orgCountSales":"1","ptCountSales":"0","region":"Брянская область","regionKey":"144235001","regionPlace":"18","rfPlace":"1535","shareRegionPercent":"1.02","urlId":"smu-stroitel-servis-6031273001"},{"apartmentsCountAll":"81","apartmentsCountSales":"79","buildingVolume":"12082","coefficientRating":"4.12","complexesCountAll":"1","complexesCountSales":"1","filteredApartmentsCount":"79","filteredComplexCount":"1","filteredGkCount":"0","filteredOrgCount":"1","filteredPtCount":"0","foundationYear":"2017","gkCountSales":"1","id":"8326769001","maxApartmentCostM2":"34500","maxCostMillion":"3.43","minApartmentCostM2":"32500","minCostMillion":"1.43","name":"МС-БРЯНСК","orgCountAll":"1","orgCountSales":"1","ptCountSales":"0","region":"Брянская область","regionKey":"144235001","regionPlace":"20","rfPlace":"1604","shareRegionPercent":"0.95","urlId":"ms-brjansk-8326769001"},{"apartmentsCountAll":"81","apartmentsCountSales":"24","buildingVolume":"10290","coefficientRating":"3.51","complexesCountAll":"2","complexesCountSales":"1","filteredApartmentsCount":"24","filteredComplexCount":"1","filteredGkCount":"0","filteredOrgCount":"1","filteredPtCount":"0","foundationYear":"1996","gkCountSales":"1","id":"5968692001","maxApartmentCostM2":"35535","maxCostMillion":"3.05","minApartmentCostM2":"34545","minCostMillion":"1.34","name":"Строительная компания Творец","orgCountAll":"1","orgCountSales":"1","ptCountSales":"0","rating":"3.5","region":"Брянская область","regionKey":"144235001","regionPlace":"22","rfPlace":"1761","shareRegionPercent":"0.81","urlId":"stroitelnaja-kompanija-tvorec-5968692001"},{"apartmentsCountAll":"2","apartmentsCountSales":"2","buildingVolume":"7379","coefficientRating":"2.51","complexesCountAll":"1","complexesCountSales":"1","filteredApartmentsCount":"2","filteredComplexCount":"1","filteredGkCount":"0","filteredOrgCount":"1","filteredPtCount":"0","foundationYear":"1998","gkCountSales":"1","id":"6016074001","maxApartmentCostM2":"29500","maxCostMillion":"1.26","minApartmentCostM2":"29500","minCostMillion":"1.16","name":"Универсалстрой","orgCountAll":"1","orgCountSales":"1","ptCountSales":"0","region":"Брянская область","regionKey":"144235001","regionPlace":"24","rfPlace":"2113","shareRegionPercent":"0.58","urlId":"universalstroj-6016074001"},{"apartmentsCountAll":"25","apartmentsCountSales":"10","buildingVolume":"7280","coefficientRating":"2.48","complexesCountAll":"2","complexesCountSales":"1","filteredApartmentsCount":"10","filteredComplexCount":"1","filteredGkCount":"0","filteredOrgCount":"1","filteredPtCount":"0","foundationYear":"2011","gkCountSales":"1","id":"5868961001","maxApartmentCostM2":"28700","maxCostMillion":"2.62","minApartmentCostM2":"28000","minCostMillion":"1.15","name":"Брянский ОЖФ","orgCountAll":"1","orgCountSales":"1","ptCountSales":"0","rating":"2","region":"Брянская область","regionKey":"144235001","regionPlace":"25","rfPlace":"2120","shareRegionPercent":"0.57","urlId":"brjanskij-oblastnoj-zhilishhnyj-fond-5868961001"},{"apartmentsCountAll":"2","apartmentsCountSales":"1","buildingVolume":"4651","coefficientRating":"1.58","complexesCountAll":"2","complexesCountSales":"1","filteredApartmentsCount":"1","filteredComplexCount":"1","filteredGkCount":"0","filteredOrgCount":"1","filteredPtCount":"0","foundationYear":"2006","gkCountSales":"1","id":"4181077001","maxApartmentCostM2":"30500","maxCostMillion":"1.05","minApartmentCostM2":"30500","minCostMillion":"1.05","name":"Русстрой","orgCountAll":"2","orgCountSales":"1","ptCountSales":"0","region":"Брянская область","regionKey":"144235001","regionPlace":"27","rfPlace":"2566","shareRegionPercent":"0.36","urlId":"russtroj-4181077001"},{"apartmentsCountAll":"8","apartmentsCountSales":"2","buildingVolume":"4371","coefficientRating":"1.49","complexesCountAll":"4","complexesCountSales":"1","filteredApartmentsCount":"2","filteredComplexCount":"1","filteredGkCount":"0","filteredOrgCount":"1","filteredPtCount":"0","foundationYear":"1994","gkCountSales":"1","id":"5865552001","maxApartmentCostM2":"31000","maxCostMillion":"1.86","minApartmentCostM2":"30000","minCostMillion":"1.06","name":"Комплект","orgCountAll":"1","orgCountSales":"1","ptCountSales":"0","rating":"4","region":"Брянская область","regionKey":"144235001","regionPlace":"30","rfPlace":"2606","shareRegionPercent":"0.34","urlId":"komplekt-5865552001"},{"apartmentsCountAll":"77","apartmentsCountSales":"2","buildingVolume":"3696","coefficientRating":"1.26","complexesCountAll":"2","complexesCountSales":"1","filteredApartmentsCount":"2","filteredComplexCount":"1","filteredGkCount":"0","filteredOrgCount":"1","filteredPtCount":"0","foundationYear":"2017","gkCountSales":"1","id":"6945225001","maxApartmentCostM2":"30334","maxCostMillion":"1.2","minApartmentCostM2":"30319","minCostMillion":"1.13","name":"Династия","orgCountAll":"1","orgCountSales":"1","ptCountSales":"0","region":"Брянская область","regionKey":"144235001","regionPlace":"32","rfPlace":"2716","shareRegionPercent":"0.29","urlId":"-dinastija-6945225001"},{"apartmentsCountAll":"16","apartmentsCountSales":"14","buildingVolume":"3180","coefficientRating":"1.08","complexesCountAll":"1","complexesCountSales":"1","filteredApartmentsCount":"14","filteredComplexCount":"1","filteredGkCount":"0","filteredOrgCount":"1","filteredPtCount":"0","foundationYear":"2011","gkCountSales":"1","id":"8126518001","maxApartmentCostM2":"55000","maxCostMillion":"4.91","minApartmentCostM2":"45000","minCostMillion":"2.03","name":"ПАРТНЕР +","orgCountAll":"1","orgCountSales":"1","ptCountSales":"0","region":"Брянская область","regionKey":"144235001","regionPlace":"34","rfPlace":"2796","shareRegionPercent":"0.25","urlId":"-partner-+-8126518001"},{"apartmentsCountAll":"3","apartmentsCountSales":"3","buildingVolume":"3045","coefficientRating":"1.04","complexesCountAll":"1","complexesCountSales":"1","filteredApartmentsCount":"3","filteredComplexCount":"1","filteredGkCount":"0","filteredOrgCount":"1","filteredPtCount":"0","foundationYear":"2010","gkCountSales":"1","id":"6116170001","maxApartmentCostM2":"23220","maxCostMillion":"1.54","minApartmentCostM2":"23000","minCostMillion":"1.25","name":"Готика","orgCountAll":"1","orgCountSales":"1","ptCountSales":"0","region":"Брянская область","regionKey":"144235001","regionPlace":"35","rfPlace":"2815","shareRegionPercent":"0.24","urlId":"gotika-6116170001"},{"apartmentsCountAll":"2","apartmentsCountSales":"2","buildingVolume":"1694","coefficientRating":"0.58","complexesCountAll":"4","complexesCountSales":"2","filteredApartmentsCount":"2","filteredComplexCount":"2","filteredGkCount":"0","filteredOrgCount":"1","filteredPtCount":"0","foundationYear":"2006","gkCountSales":"2","id":"7784234001","maxApartmentCostM2":"29000","maxCostMillion":"1.23","minApartmentCostM2":"27569","minCostMillion":"1.1","name":"Русский дом","orgCountAll":"1","orgCountSales":"1","ptCountSales":"0","region":"Брянская область","regionKey":"144235001","regionPlace":"36","rfPlace":"3077","shareRegionPercent":"0.13","urlId":"-russkij-dom-7784234001"},{"apartmentsCountAll":"2","apartmentsCountSales":"2","buildingVolume":"1467","coefficientRating":"0.5","complexesCountAll":"1","complexesCountSales":"1","filteredApartmentsCount":"2","filteredComplexCount":"1","filteredGkCount":"0","filteredOrgCount":"1","filteredPtCount":"0","foundationYear":"1995","gkCountSales":"1","id":"8464031001","maxApartmentCostM2":"28000","maxCostMillion":"1.03","minApartmentCostM2":"28000","minCostMillion":"1.03","name":"Стройкомплект","orgCountAll":"1","orgCountSales":"1","ptCountSales":"0","region":"Брянская область","regionKey":"144235001","regionPlace":"37","rfPlace":"3110","shareRegionPercent":"0.11","urlId":"-strojkomplekt-8464031001"},{"apartmentsCountAll":"1","apartmentsCountSales":"1","complexesCountAll":"1","complexesCountSales":"1","filteredApartmentsCount":"1","filteredComplexCount":"1","filteredGkCount":"0","filteredOrgCount":"1","filteredPtCount":"0","foundationYear":"2014","gkCountSales":"1","id":"8219912001","maxApartmentCostM2":"37000","maxCostMillion":"1.76","minApartmentCostM2":"37000","minCostMillion":"1.76","name":"РЕГИОНСПЕЦСТРОЙ","orgCountAll":"1","orgCountSales":"1","ptCountSales":"0","region":"Брянская область","regionKey":"144235001","urlId":"regionspecstroj-8219912001"},{"apartmentsCountAll":"24","apartmentsCountSales":"19","complexesCountAll":"1","complexesCountSales":"1","filteredApartmentsCount":"19","filteredComplexCount":"1","filteredGkCount":"0","filteredOrgCount":"1","filteredPtCount":"0","foundationYear":"1993","gkCountSales":"1","id":"5881977001","maxApartmentCostM2":"33519","maxCostMillion":"3.51","minApartmentCostM2":"26000","minCostMillion":"1.66","name":"Техномикс","orgCountAll":"1","orgCountSales":"1","ptCountSales":"0","region":"Брянская область","regionKey":"144235001","urlId":"tekhnomiks-5881977001"},{"apartmentsCountAll":"4","apartmentsCountSales":"4","complexesCountAll":"1","complexesCountSales":"1","filteredApartmentsCount":"4","filteredComplexCount":"1","filteredGkCount":"0","filteredOrgCount":"1","filteredPtCount":"0","foundationYear":"2013","gkCountSales":"1","id":"8455990001","maxApartmentCostM2":"27000","maxCostMillion":"1.86","minApartmentCostM2":"26000","minCostMillion":"1.16","name":"Унечское ПМК-226","orgCountAll":"1","orgCountSales":"1","ptCountSales":"0","region":"Брянская область","regionKey":"144235001","urlId":"-unechskoe-pmk-226-8455990001"},{"apartmentsCountAll":"1","apartmentsCountSales":"1","complexesCountAll":"1","complexesCountSales":"1","filteredApartmentsCount":"1","filteredComplexCount":"1","filteredGkCount":"0","filteredOrgCount":"1","filteredPtCount":"0","foundationYear":"2001","gkCountSales":"1","id":"8457651001","maxApartmentCostM2":"30500","maxCostMillion":"1.19","minApartmentCostM2":"30500","minCostMillion":"1.19","name":"СК Стройград","orgCountAll":"1","orgCountSales":"1","ptCountSales":"0","region":"Брянская область","regionKey":"144235001","urlId":"-stroitelnaja-kompanija-strojgrad-8457651001"},{"apartmentsCountAll":"102","apartmentsCountSales":"2","complexesCountAll":"4","complexesCountSales":"1","filteredApartmentsCount":"2","filteredComplexCount":"1","filteredGkCount":"0","filteredOrgCount":"1","filteredPtCount":"0","foundationYear":"2008","gkCountSales":"1","id":"5884780001","maxApartmentCostM2":"37000","maxCostMillion":"2.21","minApartmentCostM2":"36000","minCostMillion":"1.24","name":"Светал","orgCountAll":"1","orgCountSales":"1","ptCountSales":"0","rating":"5","region":"Брянская область","regionKey":"144235001","urlId":"svetal-5884780001"}]